<?xml version="1.0" encoding="UTF-8" standalone="yes"?><deck name="Shards of Alara"><card><name>Ad Nauseam</name><cost>3BB</cost><typelist><type>Instant</type></typelist><rulelist><rule xmlns:xsi="http://www.w3.org/2001/XMLSchema-instance" xsi:type="rule">Reveal the top card of your library and put that card into your hand. You lose life equal to its converted mana cost. You may repeat this process any number of times.</rule></rulelist></card><card><name>Agony Warp</name><cost>UB</cost><typelist><type>Instant</type></typelist><rulelist><rule xmlns:xsi="http://www.w3.org/2001/XMLSchema-instance" xsi:type="rule">Target creature gets -3/-0 until end of turn.</rule><rule xmlns:xsi="http://www.w3.org/2001/XMLSchema-instance" xsi:type="rule">Target creature gets -0/-3 until end of turn.</rule></rulelist></card><card><name>Ajani Vengeant</name><cost>2RW</cost><loyalty>3</loyalty><typelist><type>Planeswalker</type><type>Ajani</type></typelist><rulelist><rule xmlns:xsi="http://www.w3.org/2001/XMLSchema-instance" xsi:type="rule">+1: Target permanent doesn't untap during its controller's next untap step.</rule><rule xmlns:xsi="http://www.w3.org/2001/XMLSchema-instance" xsi:type="rule">-2: Ajani Vengeant deals 3 damage to target creature or player and you gain 3 life.</rule><rule xmlns:xsi="http://www.w3.org/2001/XMLSchema-instance" xsi:type="rule">-7: Destroy all lands target player controls.</rule></rulelist></card><card><name>Akrasan Squire</name><cost>W</cost><typelist><type>Creature</type><type>Human</type><type>Soldier</type></typelist><pow>1</pow><tgh>1</tgh><rulelist><rule xmlns:xsi="http://www.w3.org/2001/XMLSchema-instance" xsi:type="rule" reminder="Whenever a creature you control attacks alone, that creature gets +1/+1 until end of turn.">Exalted</rule></rulelist></card><card><name>Algae Gharial</name><cost>3G</cost><typelist><type>Creature</type><type>Crocodile</type></typelist><pow>1</pow><tgh>1</tgh><rulelist><rule xmlns:xsi="http://www.w3.org/2001/XMLSchema-instance" xsi:type="rule">Shroud</rule><rule xmlns:xsi="http://www.w3.org/2001/XMLSchema-instance" xsi:type="rule">Whenever another creature is put into a graveyard from the battlefield, you may put a +1/+1 counter on Algae Gharial.</rule></rulelist></card><card><name>Angel's Herald</name><cost>W</cost><typelist><type>Creature</type><type>Human</type><type>Cleric</type></typelist><pow>1</pow><tgh>1</tgh><rulelist><rule xmlns:xsi="http://www.w3.org/2001/XMLSchema-instance" xsi:type="rule">{2}{W}, {T}, Sacrifice a green creature, a white creature, and a blue creature: Search your library for a card named Empyrial Archangel and put it onto the battlefield. Then shuffle your library.</rule></rulelist></card><card><name>Angelic Benediction</name><cost>3W</cost><typelist><type>Enchantment</type></typelist><rulelist><rule xmlns:xsi="http://www.w3.org/2001/XMLSchema-instance" xsi:type="rule" reminder="Whenever a creature you control attacks alone, that creature gets +1/+1 until end of turn.">Exalted</rule><rule xmlns:xsi="http://www.w3.org/2001/XMLSchema-instance" xsi:type="rule">Whenever a creature you control attacks alone, you may tap target creature.</rule></rulelist></card><card><name>Angelsong</name><cost>1W</cost><typelist><type>Instant</type></typelist><rulelist><rule xmlns:xsi="http://www.w3.org/2001/XMLSchema-instance" xsi:type="rule">Prevent all combat damage that would be dealt this turn.</rule><rule xmlns:xsi="http://www.w3.org/2001/XMLSchema-instance" xsi:type="rule" reminder="{2}, Discard this card: Draw a card.">Cycling {2}</rule></rulelist></card><card><name>Arcane Sanctum</name><typelist><type>Land</type></typelist><rulelist><rule xmlns:xsi="http://www.w3.org/2001/XMLSchema-instance" xsi:type="rule">Arcane Sanctum enters the battlefield tapped.</rule><rule xmlns:xsi="http://www.w3.org/2001/XMLSchema-instance" xsi:type="rule">{T}: Add {W}, {U}, or {B} to your mana pool.</rule></rulelist></card><card><name>Archdemon of Unx</name><cost>5BB</cost><typelist><type>Creature</type><type>Demon</type></typelist><pow>6</pow><tgh>6</tgh><rulelist><rule xmlns:xsi="http://www.w3.org/2001/XMLSchema-instance" xsi:type="rule">Flying, trample</rule><rule xmlns:xsi="http://www.w3.org/2001/XMLSchema-instance" xsi:type="rule">At the beginning of your upkeep, sacrifice a non-Zombie creature, then put a 2/2 black Zombie creature token onto the battlefield.</rule></rulelist></card><card><name>Banewasp Affliction</name><cost>1B</cost><typelist><type>Enchantment</type><type>Aura</type></typelist><rulelist><rule xmlns:xsi="http://www.w3.org/2001/XMLSchema-instance" xsi:type="rule">Enchant creature</rule><rule xmlns:xsi="http://www.w3.org/2001/XMLSchema-instance" xsi:type="rule">When enchanted creature is put into a graveyard, that creature's controller loses life equal to its toughness.</rule></rulelist></card><card><name>Bant Battlemage</name><cost>2W</cost><typelist><type>Creature</type><type>Human</type><type>Wizard</type></typelist><pow>2</pow><tgh>2</tgh><rulelist><rule xmlns:xsi="http://www.w3.org/2001/XMLSchema-instance" xsi:type="rule">{G}, {T}: Target creature gains trample until end of turn.</rule><rule xmlns:xsi="http://www.w3.org/2001/XMLSchema-instance" xsi:type="rule">{U}, {T}: Target creature gains flying until end of turn.</rule></rulelist></card><card><name>Bant Charm</name><cost>GWU</cost><typelist><type>Instant</type></typelist><rulelist><rule xmlns:xsi="http://www.w3.org/2001/XMLSchema-instance" xsi:type="rule">Choose one — Destroy target artifact; or put target creature on the bottom of its owner's library; or counter target instant spell.</rule></rulelist></card><card><name>Bant Panorama</name><typelist><type>Land</type></typelist><rulelist><rule xmlns:xsi="http://www.w3.org/2001/XMLSchema-instance" xsi:type="rule">{T}: Add {1} to your mana pool.</rule><rule xmlns:xsi="http://www.w3.org/2001/XMLSchema-instance" xsi:type="rule">{1}, {T}, Sacrifice Bant Panorama: Search your library for a basic Forest, Plains, or Island card and put it onto the battlefield tapped. Then shuffle your library.</rule></rulelist></card><card><name>Battlegrace Angel</name><cost>3WW</cost><typelist><type>Creature</type><type>Angel</type></typelist><pow>4</pow><tgh>4</tgh><rulelist><rule xmlns:xsi="http://www.w3.org/2001/XMLSchema-instance" xsi:type="rule">Flying</rule><rule xmlns:xsi="http://www.w3.org/2001/XMLSchema-instance" xsi:type="rule" reminder="Whenever a creature you control attacks alone, that creature gets +1/+1 until end of turn.">Exalted</rule><rule xmlns:xsi="http://www.w3.org/2001/XMLSchema-instance" xsi:type="rule">Whenever a creature you control attacks alone, it gains lifelink until end of turn.</rule></rulelist></card><card><name>Behemoth's Herald</name><cost>G</cost><typelist><type>Creature</type><type>Elf</type><type>Shaman</type></typelist><pow>1</pow><tgh>1</tgh><rulelist><rule xmlns:xsi="http://www.w3.org/2001/XMLSchema-instance" xsi:type="rule">{2}{G}, {T}, Sacrifice a red creature, a green creature, and a white creature: Search your library for a card named Godsire and put it onto the battlefield. Then shuffle your library.</rule></rulelist></card><card><name>Blightning</name><cost>1BR</cost><typelist><type>Sorcery</type></typelist><rulelist><rule xmlns:xsi="http://www.w3.org/2001/XMLSchema-instance" xsi:type="rule">Blightning deals 3 damage to target player. That player discards two cards.</rule></rulelist></card><card><name>Blister Beetle</name><cost>1B</cost><typelist><type>Creature</type><type>Insect</type></typelist><pow>1</pow><tgh>1</tgh><rulelist><rule xmlns:xsi="http://www.w3.org/2001/XMLSchema-instance" xsi:type="rule">When Blister Beetle enters the battlefield, target creature gets -1/-1 until end of turn.</rule></rulelist></card><card><name>Blood Cultist</name><cost>1BR</cost><typelist><type>Creature</type><type>Human</type><type>Wizard</type></typelist><pow>1</pow><tgh>1</tgh><rulelist><rule xmlns:xsi="http://www.w3.org/2001/XMLSchema-instance" xsi:type="rule">{T}: Blood Cultist deals 1 damage to target creature.</rule><rule xmlns:xsi="http://www.w3.org/2001/XMLSchema-instance" xsi:type="rule">Whenever a creature dealt damage by Blood Cultist this turn is put into a graveyard, put a +1/+1 counter on Blood Cultist.</rule></rulelist></card><card><name>Bloodpyre Elemental</name><cost>4R</cost><typelist><type>Creature</type><type>Elemental</type></typelist><pow>4</pow><tgh>1</tgh><rulelist><rule xmlns:xsi="http://www.w3.org/2001/XMLSchema-instance" xsi:type="rule">Sacrifice Bloodpyre Elemental: Bloodpyre Elemental deals 4 damage to target creature. Activate this ability only any time you could cast a sorcery.</rule></rulelist></card><card><name>Bloodthorn Taunter</name><cost>1R</cost><typelist><type>Creature</type><type>Human</type><type>Scout</type></typelist><pow>1</pow><tgh>1</tgh><rulelist><rule xmlns:xsi="http://www.w3.org/2001/XMLSchema-instance" xsi:type="rule">Haste</rule><rule xmlns:xsi="http://www.w3.org/2001/XMLSchema-instance" xsi:type="rule">{T}: Target creature with power 5 or greater gains haste until end of turn.</rule></rulelist></card><card><name>Bone Splinters</name><cost>B</cost><typelist><type>Sorcery</type></typelist><rulelist><rule xmlns:xsi="http://www.w3.org/2001/XMLSchema-instance" xsi:type="rule">As an additional cost to cast Bone Splinters, sacrifice a creature.</rule><rule xmlns:xsi="http://www.w3.org/2001/XMLSchema-instance" xsi:type="rule">Destroy target creature.</rule></rulelist></card><card><name>Branching Bolt</name><cost>1RG</cost><typelist><type>Instant</type></typelist><rulelist><rule xmlns:xsi="http://www.w3.org/2001/XMLSchema-instance" xsi:type="rule">Choose one or both — Branching Bolt deals 3 damage to target creature with flying; and/or Branching Bolt deals 3 damage to target creature without flying.</rule></rulelist></card><card><name>Brilliant Ultimatum</name><cost>WWUUUBB</cost><typelist><type>Sorcery</type></typelist><rulelist><rule xmlns:xsi="http://www.w3.org/2001/XMLSchema-instance" xsi:type="rule">Exile the top five cards of your library. An opponent separates those cards into two piles. You may play any number of cards from one of those piles without paying their mana costs.</rule></rulelist></card><card><name>Broodmate Dragon</name><cost>3BRG</cost><typelist><type>Creature</type><type>Dragon</type></typelist><pow>4</pow><tgh>4</tgh><rulelist><rule xmlns:xsi="http://www.w3.org/2001/XMLSchema-instance" xsi:type="rule">Flying</rule><rule xmlns:xsi="http://www.w3.org/2001/XMLSchema-instance" xsi:type="rule">When Broodmate Dragon enters the battlefield, put a 4/4 red Dragon creature token with flying onto the battlefield.</rule></rulelist></card><card><name>Bull Cerodon</name><cost>4RW</cost><typelist><type>Creature</type><type>Beast</type></typelist><pow>5</pow><tgh>5</tgh><rulelist><rule xmlns:xsi="http://www.w3.org/2001/XMLSchema-instance" xsi:type="rule">Vigilance, haste</rule></rulelist></card><card><name>Caldera Hellion</name><cost>3RR</cost><typelist><type>Creature</type><type>Hellion</type></typelist><pow>3</pow><tgh>3</tgh><rulelist><rule xmlns:xsi="http://www.w3.org/2001/XMLSchema-instance" xsi:type="rule" reminder="As this enters the battlefield, you may sacrifice any number of creatures. This creature enters the battlefield with that many +1/+1 counters on it.">Devour 1</rule><rule xmlns:xsi="http://www.w3.org/2001/XMLSchema-instance" xsi:type="rule">When Caldera Hellion enters the battlefield, it deals 3 damage to each creature.</rule></rulelist></card><card><name>Call to Heel</name><cost>1U</cost><typelist><type>Instant</type></typelist><rulelist><rule xmlns:xsi="http://www.w3.org/2001/XMLSchema-instance" xsi:type="rule">Return target creature to its owner's hand. Its controller draws a card.</rule></rulelist></card><card><name>Cancel</name><cost>1UU</cost><typelist><type>Instant</type></typelist><rulelist><rule xmlns:xsi="http://www.w3.org/2001/XMLSchema-instance" xsi:type="rule">Counter target spell.</rule></rulelist></card><card><name>Carrion Thrash</name><cost>2BRG</cost><typelist><type>Creature</type><type>Viashino</type><type>Warrior</type></typelist><pow>4</pow><tgh>4</tgh><rulelist><rule xmlns:xsi="http://www.w3.org/2001/XMLSchema-instance" xsi:type="rule">When Carrion Thrash is put into a graveyard from the battlefield, you may pay {2}. If you do, return another target creature card from your graveyard to your hand.</rule></rulelist></card><card><name>Cathartic Adept</name><cost>U</cost><typelist><type>Creature</type><type>Human</type><type>Wizard</type></typelist><pow>1</pow><tgh>1</tgh><rulelist><rule xmlns:xsi="http://www.w3.org/2001/XMLSchema-instance" xsi:type="rule">{T}: Target player puts the top card of his or her library into his or her graveyard.</rule></rulelist></card><card><name>Cavern Thoctar</name><cost>5G</cost><typelist><type>Creature</type><type>Beast</type></typelist><pow>5</pow><tgh>5</tgh><rulelist><rule xmlns:xsi="http://www.w3.org/2001/XMLSchema-instance" xsi:type="rule">{1}{R}: Cavern Thoctar gets +1/+0 until end of turn.</rule></rulelist></card><card><name>Clarion Ultimatum</name><cost>GGWWWUU</cost><typelist><type>Sorcery</type></typelist><rulelist><rule xmlns:xsi="http://www.w3.org/2001/XMLSchema-instance" xsi:type="rule">ay search your library for a card with the same name as that permanent. Put those cards onto the battlefield tapped, then shuffle your library.</rule></rulelist></card><card><name>Cloudheath Drake</name><cost>4U</cost><typelist><type>Artifact</type><type>Creature</type><type>Drake</type></typelist><pow>3</pow><tgh>3</tgh><rulelist><rule xmlns:xsi="http://www.w3.org/2001/XMLSchema-instance" xsi:type="rule">Flying</rule><rule xmlns:xsi="http://www.w3.org/2001/XMLSchema-instance" xsi:type="rule">{1}{W}: Cloudheath Drake gains vigilance until end of turn.</rule></rulelist></card><card><name>Coma Veil</name><cost>4U</cost><typelist><type>Enchantment</type><type>Aura</type></typelist><rulelist><rule xmlns:xsi="http://www.w3.org/2001/XMLSchema-instance" xsi:type="rule">Enchant artifact or creature</rule><rule xmlns:xsi="http://www.w3.org/2001/XMLSchema-instance" xsi:type="rule">Enchanted permanent doesn't untap during its controller's untap step.</rule></rulelist></card><card><name>Corpse Connoisseur</name><cost>4B</cost><typelist><type>Creature</type><type>Zombie</type><type>Wizard</type></typelist><pow>3</pow><tgh>3</tgh><rulelist><rule xmlns:xsi="http://www.w3.org/2001/XMLSchema-instance" xsi:type="rule">When Corpse Connoisseur enters the battlefield, you may search your library for a creature card and put that card into your graveyard. If you do, shuffle your library.</rule><rule xmlns:xsi="http://www.w3.org/2001/XMLSchema-instance" xsi:type="rule" reminder="{3}{B}: Return this card from your graveyard to the battlefield. It gains haste. Exile it at the beginning of the next end step or if it would leave the battlefield. Unearth only as a sorcery.">Unearth {3}{B}</rule></rulelist></card><card><name>Courier's Capsule</name><cost>1U</cost><typelist><type>Artifact</type></typelist><rulelist><rule xmlns:xsi="http://www.w3.org/2001/XMLSchema-instance" xsi:type="rule">{1}{U}, {T}, Sacrifice Courier's Capsule: Draw two cards.</rule></rulelist></card><card><name>Court Archers</name><cost>2G</cost><typelist><type>Creature</type><type>Human</type><type>Archer</type></typelist><pow>1</pow><tgh>3</tgh><rulelist><rule xmlns:xsi="http://www.w3.org/2001/XMLSchema-instance" xsi:type="rule" reminder="This can block creatures with flying.">Reach</rule><rule xmlns:xsi="http://www.w3.org/2001/XMLSchema-instance" xsi:type="rule" reminder="Whenever a creature you control attacks alone, that creature gets +1/+1 until end of turn.">Exalted</rule></rulelist></card><card><name>Covenant of Minds</name><cost>4U</cost><typelist><type>Sorcery</type></typelist><rulelist><rule xmlns:xsi="http://www.w3.org/2001/XMLSchema-instance" xsi:type="rule">Reveal the top three cards of your library. Target opponent may choose to put those cards into your hand. If he or she doesn't, put those cards into your graveyard and draw five cards.</rule></rulelist></card><card><name>Cradle of Vitality</name><cost>3W</cost><typelist><type>Enchantment</type></typelist><rulelist><rule xmlns:xsi="http://www.w3.org/2001/XMLSchema-instance" xsi:type="rule">Whenever you gain life, you may pay {1}{W}. If you do, put a +1/+1 counter on target creature for each 1 life you gained.</rule></rulelist></card><card><name>Crucible of Fire</name><cost>3R</cost><typelist><type>Enchantment</type></typelist><rulelist><rule xmlns:xsi="http://www.w3.org/2001/XMLSchema-instance" xsi:type="rule">Dragon creatures you control get +3/+3.</rule></rulelist></card><card><name>Cruel Ultimatum</name><cost>UUBBBRR</cost><typelist><type>Sorcery</type></typelist><rulelist><rule xmlns:xsi="http://www.w3.org/2001/XMLSchema-instance" xsi:type="rule">Target opponent sacrifices a creature, discards three cards, then loses 5 life. You return a creature card from your graveyard to your hand, draw three cards, then gain 5 life.</rule></rulelist></card><card><name>Crumbling Necropolis</name><typelist><type>Land</type></typelist><rulelist><rule xmlns:xsi="http://www.w3.org/2001/XMLSchema-instance" xsi:type="rule">Crumbling Necropolis enters the battlefield tapped.</rule><rule xmlns:xsi="http://www.w3.org/2001/XMLSchema-instance" xsi:type="rule">{T}: Add {U}, {B}, or {R} to your mana pool.</rule></rulelist></card><card><name>Cunning Lethemancer</name><cost>2B</cost><typelist><type>Creature</type><type>Human</type><type>Wizard</type></typelist><pow>2</pow><tgh>2</tgh><rulelist><rule xmlns:xsi="http://www.w3.org/2001/XMLSchema-instance" xsi:type="rule">At the beginning of your upkeep, each player discards a card.</rule></rulelist></card><card><name>Cylian Elf</name><cost>1G</cost><typelist><type>Creature</type><type>Elf</type><type>Scout</type></typelist><pow>2</pow><tgh>2</tgh></card><card><name>Dawnray Archer</name><cost>2U</cost><typelist><type>Creature</type><type>Human</type><type>Archer</type></typelist><pow>1</pow><tgh>1</tgh><rulelist><rule xmlns:xsi="http://www.w3.org/2001/XMLSchema-instance" xsi:type="rule" reminder="Whenever a creature you control attacks alone, that creature gets +1/+1 until end of turn.">Exalted</rule><rule xmlns:xsi="http://www.w3.org/2001/XMLSchema-instance" xsi:type="rule">{W}, {T}: Dawnray Archer deals 1 damage to target attacking or blocking creature.</rule></rulelist></card><card><name>Death Baron</name><cost>1BB</cost><typelist><type>Creature</type><type>Zombie</type><type>Wizard</type></typelist><pow>2</pow><tgh>2</tgh><rulelist><rule xmlns:xsi="http://www.w3.org/2001/XMLSchema-instance" xsi:type="rule">Skeleton creatures you control and other Zombie creatures you control get +1/+1 and have deathtouch.</rule></rulelist></card><card><name>Deathgreeter</name><cost>B</cost><typelist><type>Creature</type><type>Human</type><type>Shaman</type></typelist><pow>1</pow><tgh>1</tgh><rulelist><rule xmlns:xsi="http://www.w3.org/2001/XMLSchema-instance" xsi:type="rule">Whenever another creature is put into a graveyard from the battlefield, you may gain 1 life.</rule></rulelist></card><card><name>Deft Duelist</name><cost>WU</cost><typelist><type>Creature</type><type>Human</type><type>Rogue</type></typelist><pow>2</pow><tgh>1</tgh><rulelist><rule xmlns:xsi="http://www.w3.org/2001/XMLSchema-instance" xsi:type="rule">First strike</rule><rule xmlns:xsi="http://www.w3.org/2001/XMLSchema-instance" xsi:type="rule" reminder="This creature can't be the target of spells or abilities.">Shroud</rule></rulelist></card><card><name>Demon's Herald</name><cost>B</cost><typelist><type>Creature</type><type>Human</type><type>Wizard</type></typelist><pow>1</pow><tgh>1</tgh><rulelist><rule xmlns:xsi="http://www.w3.org/2001/XMLSchema-instance" xsi:type="rule">{2}{B}, {T}, Sacrifice a blue creature, a black creature, and a red creature: Search your library for a card named Prince of Thralls and put it onto the battlefield. Then shuffle your library.</rule></rulelist></card><card><name>Dispeller's Capsule</name><cost>W</cost><typelist><type>Artifact</type></typelist><rulelist><rule xmlns:xsi="http://www.w3.org/2001/XMLSchema-instance" xsi:type="rule">{2}{W}, {T}, Sacrifice Dispeller's Capsule: Destroy target artifact or enchantment.</rule></rulelist></card><card><name>Dragon Fodder</name><cost>1R</cost><typelist><type>Sorcery</type></typelist><rulelist><rule xmlns:xsi="http://www.w3.org/2001/XMLSchema-instance" xsi:type="rule">Put two 1/1 red Goblin creature tokens onto the battlefield.</rule></rulelist></card><card><name>Dragon's Herald</name><cost>R</cost><typelist><type>Creature</type><type>Goblin</type><type>Shaman</type></typelist><pow>1</pow><tgh>1</tgh><rulelist><rule xmlns:xsi="http://www.w3.org/2001/XMLSchema-instance" xsi:type="rule">{2}{R}, {T}, Sacrifice a black creature, a red creature, and a green creature: Search your library for a card named Hellkite Overlord and put it onto the battlefield. Then shuffle your library.</rule></rulelist></card><card><name>Dreg Reaver</name><cost>4B</cost><typelist><type>Creature</type><type>Zombie</type><type>Beast</type></typelist><pow>4</pow><tgh>3</tgh></card><card><name>Dregscape Zombie</name><cost>1B</cost><typelist><type>Creature</type><type>Zombie</type></typelist><pow>2</pow><tgh>1</tgh><rulelist><rule xmlns:xsi="http://www.w3.org/2001/XMLSchema-instance" xsi:type="rule" reminder="{B}: Return this card from your graveyard to the battlefield. It gains haste. Exile it at the beginning of the next end step or if it would leave the battlefield. Unearth only as a sorcery.">Unearth {B}</rule></rulelist></card><card><name>Drumhunter</name><cost>3G</cost><typelist><type>Creature</type><type>Human</type><type>Druid</type><type>Warrior</type></typelist><pow>2</pow><tgh>2</tgh><rulelist><rule xmlns:xsi="http://www.w3.org/2001/XMLSchema-instance" xsi:type="rule">At the beginning of your end step, if you control a creature with power 5 or greater, you may draw a card.</rule><rule xmlns:xsi="http://www.w3.org/2001/XMLSchema-instance" xsi:type="rule">{T}: Add {1} to your mana pool.</rule></rulelist></card><card><name>Elspeth, Knight-Errant</name><cost>2WW</cost><loyalty>4</loyalty><typelist><type>Planeswalker</type><type>Elspeth</type></typelist><rulelist><rule xmlns:xsi="http://www.w3.org/2001/XMLSchema-instance" xsi:type="rule">+1: Put a 1/1 white Soldier creature token onto the battlefield.</rule><rule xmlns:xsi="http://www.w3.org/2001/XMLSchema-instance" xsi:type="rule">+1: Target creature gets +3/+3 and gains flying until end of turn.</rule><rule xmlns:xsi="http://www.w3.org/2001/XMLSchema-instance" xsi:type="rule">creatures, enchantments, and lands you control are indestructible.&quot;</rule></rulelist></card><card><name>Elvish Visionary</name><cost>1G</cost><typelist><type>Creature</type><type>Elf</type><type>Shaman</type></typelist><pow>1</pow><tgh>1</tgh><rulelist><rule xmlns:xsi="http://www.w3.org/2001/XMLSchema-instance" xsi:type="rule">When Elvish Visionary enters the battlefield, draw a card.</rule></rulelist></card><card><name>Empyrial Archangel</name><cost>4GWWU</cost><typelist><type>Creature</type><type>Angel</type></typelist><pow>5</pow><tgh>8</tgh><rulelist><rule xmlns:xsi="http://www.w3.org/2001/XMLSchema-instance" xsi:type="rule">Flying, shroud</rule><rule xmlns:xsi="http://www.w3.org/2001/XMLSchema-instance" xsi:type="rule">All damage that would be dealt to you is dealt to Empyrial Archangel instead.</rule></rulelist></card><card><name>Esper Battlemage</name><cost>2U</cost><typelist><type>Artifact</type><type>Creature</type><type>Human</type><type>Wizard</type></typelist><pow>2</pow><tgh>2</tgh><rulelist><rule xmlns:xsi="http://www.w3.org/2001/XMLSchema-instance" xsi:type="rule">{W}, {T}: Prevent the next 2 damage that would be dealt to you this turn.</rule><rule xmlns:xsi="http://www.w3.org/2001/XMLSchema-instance" xsi:type="rule">{B}, {T}: Target creature gets -1/-1 until end of turn.</rule></rulelist></card><card><name>Esper Charm</name><cost>WUB</cost><typelist><type>Instant</type></typelist><rulelist><rule xmlns:xsi="http://www.w3.org/2001/XMLSchema-instance" xsi:type="rule">Choose one — Destroy target enchantment; or draw two cards; or target player discards two cards.</rule></rulelist></card><card><name>Esper Panorama</name><typelist><type>Land</type></typelist><rulelist><rule xmlns:xsi="http://www.w3.org/2001/XMLSchema-instance" xsi:type="rule">{T}: Add {1} to your mana pool.</rule><rule xmlns:xsi="http://www.w3.org/2001/XMLSchema-instance" xsi:type="rule">{1}, {T}, Sacrifice Esper Panorama: Search your library for a basic Plains, Island, or Swamp card and put it onto the battlefield tapped. Then shuffle your library.</rule></rulelist></card><card><name>Etherium Astrolabe</name><cost>2U</cost><typelist><type>Artifact</type></typelist><rulelist><rule xmlns:xsi="http://www.w3.org/2001/XMLSchema-instance" xsi:type="rule">Flash</rule><rule xmlns:xsi="http://www.w3.org/2001/XMLSchema-instance" xsi:type="rule">{B}, {T}, Sacrifice an artifact: Draw a card.</rule></rulelist></card><card><name>Etherium Sculptor</name><cost>1U</cost><typelist><type>Artifact</type><type>Creature</type><type>Vedalken</type><type>Artificer</type></typelist><pow>1</pow><tgh>2</tgh><rulelist><rule xmlns:xsi="http://www.w3.org/2001/XMLSchema-instance" xsi:type="rule">Artifact spells you cast cost {1} less to cast.</rule></rulelist></card><card><name>Ethersworn Canonist</name><cost>1W</cost><typelist><type>Artifact</type><type>Creature</type><type>Human</type><type>Cleric</type></typelist><pow>2</pow><tgh>2</tgh><rulelist><rule xmlns:xsi="http://www.w3.org/2001/XMLSchema-instance" xsi:type="rule">Each player who has cast a nonartifact spell this turn can't cast additional nonartifact spells.</rule></rulelist></card><card><name>Excommunicate</name><cost>2W</cost><typelist><type>Sorcery</type></typelist><rulelist><rule xmlns:xsi="http://www.w3.org/2001/XMLSchema-instance" xsi:type="rule">Put target creature on top of its owner's library.</rule></rulelist></card><card><name>Executioner's Capsule</name><cost>B</cost><typelist><type>Artifact</type></typelist><rulelist><rule xmlns:xsi="http://www.w3.org/2001/XMLSchema-instance" xsi:type="rule">{1}{B}, {T}, Sacrifice Executioner's Capsule: Destroy target nonblack creature.</rule></rulelist></card><card><name>Exuberant Firestoker</name><cost>2R</cost><typelist><type>Creature</type><type>Human</type><type>Druid</type><type>Shaman</type></typelist><pow>1</pow><tgh>1</tgh><rulelist><rule xmlns:xsi="http://www.w3.org/2001/XMLSchema-instance" xsi:type="rule">At the beginning of your end step, if you control a creature with power 5 or greater, you may have Exuberant Firestoker deal 2 damage to target player.</rule><rule xmlns:xsi="http://www.w3.org/2001/XMLSchema-instance" xsi:type="rule">{T}: Add {1} to your mana pool.</rule></rulelist></card><card><name>Fatestitcher</name><cost>3U</cost><typelist><type>Creature</type><type>Zombie</type><type>Wizard</type></typelist><pow>1</pow><tgh>2</tgh><rulelist><rule xmlns:xsi="http://www.w3.org/2001/XMLSchema-instance" xsi:type="rule">{T}: You may tap or untap another target permanent.</rule><rule xmlns:xsi="http://www.w3.org/2001/XMLSchema-instance" xsi:type="rule" reminder="{U}: Return this card from your graveyard to the battlefield. It gains haste. Exile it at the beginning of the next end step or if it would leave the battlefield. Unearth only as a sorcery.">Unearth {U}</rule></rulelist></card><card><name>Filigree Sages</name><cost>3U</cost><typelist><type>Artifact</type><type>Creature</type><type>Vedalken</type><type>Wizard</type></typelist><pow>2</pow><tgh>3</tgh><rulelist><rule xmlns:xsi="http://www.w3.org/2001/XMLSchema-instance" xsi:type="rule">{2}{U}: Untap target artifact.</rule></rulelist></card><card><name>Fire-Field Ogre</name><cost>1UBR</cost><typelist><type>Creature</type><type>Ogre</type><type>Mutant</type></typelist><pow>4</pow><tgh>2</tgh><rulelist><rule xmlns:xsi="http://www.w3.org/2001/XMLSchema-instance" xsi:type="rule">First strike</rule><rule xmlns:xsi="http://www.w3.org/2001/XMLSchema-instance" xsi:type="rule" reminder="{U}{B}{R}: Return this card from your graveyard to the battlefield. It gains haste. Exile it at the beginning of the next end step or if it would leave the battlefield. Unearth only as a sorcery.">Unearth {U}{B}{R}</rule></rulelist></card><card><name>Flameblast Dragon</name><cost>4RR</cost><typelist><type>Creature</type><type>Dragon</type></typelist><pow>5</pow><tgh>5</tgh><rulelist><rule xmlns:xsi="http://www.w3.org/2001/XMLSchema-instance" xsi:type="rule">Flying</rule><rule xmlns:xsi="http://www.w3.org/2001/XMLSchema-instance" xsi:type="rule">Whenever Flameblast Dragon attacks, you may pay {X}{R}. If you do, Flameblast Dragon deals X damage to target creature or player.</rule></rulelist></card><card><name>Fleshbag Marauder</name><cost>2B</cost><typelist><type>Creature</type><type>Zombie</type><type>Warrior</type></typelist><pow>3</pow><tgh>1</tgh><rulelist><rule xmlns:xsi="http://www.w3.org/2001/XMLSchema-instance" xsi:type="rule">sacrifices a creature.</rule></rulelist></card><card><name>Forest</name><typelist><type>Basic</type><type>Land</type><type>Forest</type></typelist><rulelist><rule xmlns:xsi="http://www.w3.org/2001/XMLSchema-instance" xsi:type="rule">G</rule></rulelist></card><card><name>Forest</name><typelist><type>Basic</type><type>Land</type><type>Forest</type></typelist><rulelist><rule xmlns:xsi="http://www.w3.org/2001/XMLSchema-instance" xsi:type="rule">G</rule></rulelist></card><card><name>Forest</name><typelist><type>Basic</type><type>Land</type><type>Forest</type></typelist><rulelist><rule xmlns:xsi="http://www.w3.org/2001/XMLSchema-instance" xsi:type="rule">G</rule></rulelist></card><card><name>Forest</name><typelist><type>Basic</type><type>Land</type><type>Forest</type></typelist><rulelist><rule xmlns:xsi="http://www.w3.org/2001/XMLSchema-instance" xsi:type="rule">G</rule></rulelist></card><card><name>Gather Specimens</name><cost>3UUU</cost><typelist><type>Instant</type></typelist><rulelist><rule xmlns:xsi="http://www.w3.org/2001/XMLSchema-instance" xsi:type="rule">If a creature would enter the battlefield under an opponent's control this turn, it enters the battlefield under your control instead.</rule></rulelist></card><card><name>Gift of the Gargantuan</name><cost>2G</cost><typelist><type>Sorcery</type></typelist><rulelist><rule xmlns:xsi="http://www.w3.org/2001/XMLSchema-instance" xsi:type="rule">Look at the top four cards of your library. You may reveal a creature card and/or a land card from among them and put the revealed cards into your hand. Put the rest on the bottom of your library in any order.</rule></rulelist></card><card><name>Glaze Fiend</name><cost>1B</cost><typelist><type>Artifact</type><type>Creature</type><type>Illusion</type></typelist><pow>0</pow><tgh>1</tgh><rulelist><rule xmlns:xsi="http://www.w3.org/2001/XMLSchema-instance" xsi:type="rule">Flying</rule><rule xmlns:xsi="http://www.w3.org/2001/XMLSchema-instance" xsi:type="rule">Whenever another artifact enters the battlefield under your control, Glaze Fiend gets +2/+2 until end of turn.</rule></rulelist></card><card><name>Goblin Assault</name><cost>2R</cost><typelist><type>Enchantment</type></typelist><rulelist><rule xmlns:xsi="http://www.w3.org/2001/XMLSchema-instance" xsi:type="rule">At the beginning of your upkeep, put a 1/1 red Goblin creature token with haste onto the battlefield.</rule><rule xmlns:xsi="http://www.w3.org/2001/XMLSchema-instance" xsi:type="rule">Goblin creatures attack each turn if able.</rule></rulelist></card><card><name>Goblin Deathraiders</name><cost>BR</cost><typelist><type>Creature</type><type>Goblin</type><type>Warrior</type></typelist><pow>3</pow><tgh>1</tgh><rulelist><rule xmlns:xsi="http://www.w3.org/2001/XMLSchema-instance" xsi:type="rule">Trample</rule></rulelist></card><card><name>Goblin Mountaineer</name><cost>R</cost><typelist><type>Creature</type><type>Goblin</type><type>Scout</type></typelist><pow>1</pow><tgh>1</tgh><rulelist><rule xmlns:xsi="http://www.w3.org/2001/XMLSchema-instance" xsi:type="rule">Mountainwalk</rule></rulelist></card><card><name>Godsire</name><cost>4RGGW</cost><typelist><type>Creature</type><type>Beast</type></typelist><pow>8</pow><tgh>8</tgh><rulelist><rule xmlns:xsi="http://www.w3.org/2001/XMLSchema-instance" xsi:type="rule">Vigilance</rule><rule xmlns:xsi="http://www.w3.org/2001/XMLSchema-instance" xsi:type="rule">{T}: Put an 8/8 Beast creature token that's red, green, and white onto the battlefield.</rule></rulelist></card><card><name>Godtoucher</name><cost>3G</cost><typelist><type>Creature</type><type>Elf</type><type>Cleric</type></typelist><pow>2</pow><tgh>2</tgh><rulelist><rule xmlns:xsi="http://www.w3.org/2001/XMLSchema-instance" xsi:type="rule">age that would be dealt to target creature with power 5 or greater this turn.</rule></rulelist></card><card><name>Grixis Battlemage</name><cost>2B</cost><typelist><type>Creature</type><type>Human</type><type>Wizard</type></typelist><pow>2</pow><tgh>2</tgh><rulelist><rule xmlns:xsi="http://www.w3.org/2001/XMLSchema-instance" xsi:type="rule">{U}, {T}: Draw a card, then discard a card.</rule><rule xmlns:xsi="http://www.w3.org/2001/XMLSchema-instance" xsi:type="rule">{R}, {T}: Target creature can't block this turn.</rule></rulelist></card><card><name>Grixis Charm</name><cost>UBR</cost><typelist><type>Instant</type></typelist><rulelist><rule xmlns:xsi="http://www.w3.org/2001/XMLSchema-instance" xsi:type="rule">Choose one — Return target permanent to its owner's hand; or target creature gets -4/-4 until end of turn; or creatures you control get +2/+0 until end of turn.</rule></rulelist></card><card><name>Grixis Panorama</name><typelist><type>Land</type></typelist><rulelist><rule xmlns:xsi="http://www.w3.org/2001/XMLSchema-instance" xsi:type="rule">{T}: Add {1} to your mana pool.</rule><rule xmlns:xsi="http://www.w3.org/2001/XMLSchema-instance" xsi:type="rule">{1}, {T}, Sacrifice Grixis Panorama: Search your library for a basic Island, Swamp, or Mountain card and put it onto the battlefield tapped. Then shuffle your library.</rule></rulelist></card><card><name>Guardians of Akrasa</name><cost>2W</cost><typelist><type>Creature</type><type>Human</type><type>Soldier</type></typelist><pow>0</pow><tgh>4</tgh><rulelist><rule xmlns:xsi="http://www.w3.org/2001/XMLSchema-instance" xsi:type="rule">Defender</rule><rule xmlns:xsi="http://www.w3.org/2001/XMLSchema-instance" xsi:type="rule" reminder="Whenever a creature you control attacks alone, that creature gets +1/+1 until end of turn.">Exalted</rule></rulelist></card><card><name>Gustrider Exuberant</name><cost>2W</cost><typelist><type>Creature</type><type>Human</type><type>Wizard</type></typelist><pow>1</pow><tgh>2</tgh><rulelist><rule xmlns:xsi="http://www.w3.org/2001/XMLSchema-instance" xsi:type="rule">Flying</rule><rule xmlns:xsi="http://www.w3.org/2001/XMLSchema-instance" xsi:type="rule">Sacrifice Gustrider Exuberant: Creatures you control with power 5 or greater gain flying until end of turn.</rule></rulelist></card><card><name>Hell's Thunder</name><cost>1RR</cost><typelist><type>Creature</type><type>Elemental</type></typelist><pow>4</pow><tgh>4</tgh><rulelist><rule xmlns:xsi="http://www.w3.org/2001/XMLSchema-instance" xsi:type="rule">Flying, haste</rule><rule xmlns:xsi="http://www.w3.org/2001/XMLSchema-instance" xsi:type="rule">At the beginning of the end step, sacrifice Hell's Thunder.</rule><rule xmlns:xsi="http://www.w3.org/2001/XMLSchema-instance" xsi:type="rule" reminder="{4}{R}: Return this card from your graveyard to the battlefield. It gains haste. Exile it at the beginning of the next end step or if it would leave the battlefield. Unearth only as a sorcery.">Unearth {4}{R}</rule></rulelist></card><card><name>Hellkite Overlord</name><cost>4BRRG</cost><typelist><type>Creature</type><type>Dragon</type></typelist><pow>8</pow><tgh>8</tgh><rulelist><rule xmlns:xsi="http://www.w3.org/2001/XMLSchema-instance" xsi:type="rule">Flying, trample, haste</rule><rule xmlns:xsi="http://www.w3.org/2001/XMLSchema-instance" xsi:type="rule">{R}: Hellkite Overlord gets +1/+0 until end of turn.</rule><rule xmlns:xsi="http://www.w3.org/2001/XMLSchema-instance" xsi:type="rule">{B}{G}: Regenerate Hellkite Overlord.</rule></rulelist></card><card><name>Hindering Light</name><cost>WU</cost><typelist><type>Instant</type></typelist><rulelist><rule xmlns:xsi="http://www.w3.org/2001/XMLSchema-instance" xsi:type="rule">Counter target spell that targets you or a permanent you control.</rule><rule xmlns:xsi="http://www.w3.org/2001/XMLSchema-instance" xsi:type="rule">Draw a card.</rule></rulelist></card><card><name>Hissing Iguanar</name><cost>2R</cost><typelist><type>Creature</type><type>Lizard</type></typelist><pow>3</pow><tgh>1</tgh><rulelist><rule xmlns:xsi="http://www.w3.org/2001/XMLSchema-instance" xsi:type="rule">Whenever another creature is put into a graveyard from the battlefield, you may have Hissing Iguanar deal 1 damage to target player.</rule></rulelist></card><card><name>Immortal Coil</name><cost>2BB</cost><typelist><type>Artifact</type></typelist><rulelist><rule xmlns:xsi="http://www.w3.org/2001/XMLSchema-instance" xsi:type="rule">{T}, Exile two cards from your graveyard: Draw a card.</rule><rule xmlns:xsi="http://www.w3.org/2001/XMLSchema-instance" xsi:type="rule">t damage. Exile a card from your graveyard for each 1 damage prevented this way.</rule><rule xmlns:xsi="http://www.w3.org/2001/XMLSchema-instance" xsi:type="rule">When there are no cards in your graveyard, you lose the game.</rule></rulelist></card><card><name>Incurable Ogre</name><cost>3R</cost><typelist><type>Creature</type><type>Ogre</type><type>Mutant</type></typelist><pow>5</pow><tgh>1</tgh></card><card><name>Infest</name><cost>1BB</cost><typelist><type>Sorcery</type></typelist><rulelist><rule xmlns:xsi="http://www.w3.org/2001/XMLSchema-instance" xsi:type="rule">All creatures get -2/-2 until end of turn.</rule></rulelist></card><card><name>Invincible Hymn</name><cost>6WW</cost><typelist><type>Sorcery</type></typelist><rulelist><rule xmlns:xsi="http://www.w3.org/2001/XMLSchema-instance" xsi:type="rule">Count the number of cards in your library. Your life total becomes that number.</rule></rulelist></card><card><name>Island</name><typelist><type>Basic</type><type>Land</type><type>Island</type></typelist><rulelist><rule xmlns:xsi="http://www.w3.org/2001/XMLSchema-instance" xsi:type="rule">U</rule></rulelist></card><card><name>Island</name><typelist><type>Basic</type><type>Land</type><type>Island</type></typelist><rulelist><rule xmlns:xsi="http://www.w3.org/2001/XMLSchema-instance" xsi:type="rule">U</rule></rulelist></card><card><name>Island</name><typelist><type>Basic</type><type>Land</type><type>Island</type></typelist><rulelist><rule xmlns:xsi="http://www.w3.org/2001/XMLSchema-instance" xsi:type="rule">U</rule></rulelist></card><card><name>Island</name><typelist><type>Basic</type><type>Land</type><type>Island</type></typelist><rulelist><rule xmlns:xsi="http://www.w3.org/2001/XMLSchema-instance" xsi:type="rule">U</rule></rulelist></card><card><name>Jhessian Infiltrator</name><cost>GU</cost><typelist><type>Creature</type><type>Human</type><type>Rogue</type></typelist><pow>2</pow><tgh>2</tgh><rulelist><rule xmlns:xsi="http://www.w3.org/2001/XMLSchema-instance" xsi:type="rule">Jhessian Infiltrator is unblockable.</rule></rulelist></card><card><name>Jhessian Lookout</name><cost>1U</cost><typelist><type>Creature</type><type>Human</type><type>Scout</type></typelist><pow>2</pow><tgh>1</tgh></card><card><name>Jund Battlemage</name><cost>2R</cost><typelist><type>Creature</type><type>Human</type><type>Shaman</type></typelist><pow>2</pow><tgh>2</tgh><rulelist><rule xmlns:xsi="http://www.w3.org/2001/XMLSchema-instance" xsi:type="rule">{B}, {T}: Target player loses 1 life.</rule><rule xmlns:xsi="http://www.w3.org/2001/XMLSchema-instance" xsi:type="rule">{G}, {T}: Put a 1/1 green Saproling creature token onto the battlefield.</rule></rulelist></card><card><name>Jund Charm</name><cost>BRG</cost><typelist><type>Instant</type></typelist><rulelist><rule xmlns:xsi="http://www.w3.org/2001/XMLSchema-instance" xsi:type="rule">Choose one — Exile all cards from target player's graveyard; or Jund Charm deals 2 damage to each creature; or put two +1/+1 counters on target creature.</rule></rulelist></card><card><name>Jund Panorama</name><typelist><type>Land</type></typelist><rulelist><rule xmlns:xsi="http://www.w3.org/2001/XMLSchema-instance" xsi:type="rule">{T}: Add {1} to your mana pool.</rule><rule xmlns:xsi="http://www.w3.org/2001/XMLSchema-instance" xsi:type="rule">{1}, {T}, Sacrifice Jund Panorama: Search your library for a basic Swamp, Mountain, or Forest card and put it onto the battlefield tapped. Then shuffle your library.</rule></rulelist></card><card><name>Jungle Shrine</name><typelist><type>Land</type></typelist><rulelist><rule xmlns:xsi="http://www.w3.org/2001/XMLSchema-instance" xsi:type="rule">Jungle Shrine enters the battlefield tapped.</rule><rule xmlns:xsi="http://www.w3.org/2001/XMLSchema-instance" xsi:type="rule">{T}: Add {R}, {G}, or {W} to your mana pool.</rule></rulelist></card><card><name>Jungle Weaver</name><cost>5GG</cost><typelist><type>Creature</type><type>Spider</type></typelist><pow>5</pow><tgh>6</tgh><rulelist><rule xmlns:xsi="http://www.w3.org/2001/XMLSchema-instance" xsi:type="rule" reminder="This can block creatures with flying.">Reach</rule><rule xmlns:xsi="http://www.w3.org/2001/XMLSchema-instance" xsi:type="rule" reminder="{2}, Discard this card: Draw a card.">Cycling {2}</rule></rulelist></card><card><name>Kathari Screecher</name><cost>2U</cost><typelist><type>Creature</type><type>Bird</type><type>Soldier</type></typelist><pow>2</pow><tgh>2</tgh><rulelist><rule xmlns:xsi="http://www.w3.org/2001/XMLSchema-instance" xsi:type="rule">Flying</rule><rule xmlns:xsi="http://www.w3.org/2001/XMLSchema-instance" xsi:type="rule" reminder="{2}{U}: Return this card from your graveyard to the battlefield. It gains haste. Exile it at the beginning of the next end step or if it would leave the battlefield. Unearth only as a sorcery.">Unearth {2}{U}</rule></rulelist></card><card><name>Kederekt Creeper</name><cost>UBR</cost><typelist><type>Creature</type><type>Horror</type></typelist><pow>2</pow><tgh>3</tgh><rulelist><rule xmlns:xsi="http://www.w3.org/2001/XMLSchema-instance" xsi:type="rule" reminder="Any amount of damage this deals to a creature is enough to destroy it.">Deathtouch</rule><rule xmlns:xsi="http://www.w3.org/2001/XMLSchema-instance" xsi:type="rule">Kederekt Creeper can't be blocked except by two or more creatures.</rule></rulelist></card><card><name>Kederekt Leviathan</name><cost>6UU</cost><typelist><type>Creature</type><type>Leviathan</type></typelist><pow>5</pow><tgh>5</tgh><rulelist><rule xmlns:xsi="http://www.w3.org/2001/XMLSchema-instance" xsi:type="rule">When Kederekt Leviathan enters the battlefield, return all other nonland permanents to their owners' hands.</rule><rule xmlns:xsi="http://www.w3.org/2001/XMLSchema-instance" xsi:type="rule" reminder="{6}{U}: Return this card from your graveyard to the battlefield. It gains haste. Exile it at the beginning of the next end step or if it would leave the battlefield. Unearth only as a sorcery.">Unearth {6}{U}</rule></rulelist></card><card><name>Keeper of Progenitus</name><cost>3G</cost><typelist><type>Creature</type><type>Elf</type><type>Druid</type></typelist><pow>1</pow><tgh>3</tgh><rulelist><rule xmlns:xsi="http://www.w3.org/2001/XMLSchema-instance" xsi:type="rule">Whenever a player taps a Mountain, Forest, or Plains for mana, that player adds one mana to his or her mana pool of any type that land produced.</rule></rulelist></card><card><name>Kiss of the Amesha</name><cost>4WU</cost><typelist><type>Sorcery</type></typelist><rulelist><rule xmlns:xsi="http://www.w3.org/2001/XMLSchema-instance" xsi:type="rule">Target player gains 7 life and draws two cards.</rule></rulelist></card><card><name>Knight of the Skyward Eye</name><cost>1W</cost><typelist><type>Creature</type><type>Human</type><type>Knight</type></typelist><pow>2</pow><tgh>2</tgh><rulelist><rule xmlns:xsi="http://www.w3.org/2001/XMLSchema-instance" xsi:type="rule">{3}{G}: Knight of the Skyward Eye gets +3/+3 until end of turn. Activate this ability only once each turn.</rule></rulelist></card><card><name>Knight of the White Orchid</name><cost>WW</cost><typelist><type>Creature</type><type>Human</type><type>Knight</type></typelist><pow>2</pow><tgh>2</tgh><rulelist><rule xmlns:xsi="http://www.w3.org/2001/XMLSchema-instance" xsi:type="rule">First strike</rule><rule xmlns:xsi="http://www.w3.org/2001/XMLSchema-instance" xsi:type="rule">When Knight of the White Orchid enters the battlefield, if an opponent controls more lands than you, you may search your library for a Plains card, put it onto the battlefield, then shuffle your library.</rule></rulelist></card><card><name>Knight-Captain of Eos</name><cost>4W</cost><typelist><type>Creature</type><type>Human</type><type>Knight</type></typelist><pow>2</pow><tgh>2</tgh><rulelist><rule xmlns:xsi="http://www.w3.org/2001/XMLSchema-instance" xsi:type="rule">ure tokens onto the battlefield.</rule><rule xmlns:xsi="http://www.w3.org/2001/XMLSchema-instance" xsi:type="rule">{W}, Sacrifice a Soldier: Prevent all combat damage that would be dealt this turn.</rule></rulelist></card><card><name>Kresh the Bloodbraided</name><cost>2BRG</cost><typelist><type>Legendary</type><type>Creature</type><type>Human</type><type>Warrior</type></typelist><pow>3</pow><tgh>3</tgh><rulelist><rule xmlns:xsi="http://www.w3.org/2001/XMLSchema-instance" xsi:type="rule">Whenever another creature is put into a graveyard from the battlefield, you may put X +1/+1 counters on Kresh the Bloodbraided, where X is that creature's power.</rule></rulelist></card><card><name>Lich's Mirror</name><cost>5</cost><typelist><type>Artifact</type></typelist><rulelist><rule xmlns:xsi="http://www.w3.org/2001/XMLSchema-instance" xsi:type="rule">If you would lose the game, instead shuffle your hand, your graveyard, and all permanents you own into your library, then draw seven cards and your life total becomes 20.</rule></rulelist></card><card><name>Lightning Talons</name><cost>2R</cost><typelist><type>Enchantment</type><type>Aura</type></typelist><rulelist><rule xmlns:xsi="http://www.w3.org/2001/XMLSchema-instance" xsi:type="rule">Enchant creature</rule><rule xmlns:xsi="http://www.w3.org/2001/XMLSchema-instance" xsi:type="rule">Enchanted creature gets +3/+0 and has first strike.</rule></rulelist></card><card><name>Lush Growth</name><cost>G</cost><typelist><type>Enchantment</type><type>Aura</type></typelist><rulelist><rule xmlns:xsi="http://www.w3.org/2001/XMLSchema-instance" xsi:type="rule">Enchant land</rule><rule xmlns:xsi="http://www.w3.org/2001/XMLSchema-instance" xsi:type="rule">Enchanted land is a Mountain, Forest, and Plains.</rule></rulelist></card><card><name>Magma Spray</name><cost>R</cost><typelist><type>Instant</type></typelist><rulelist><rule xmlns:xsi="http://www.w3.org/2001/XMLSchema-instance" xsi:type="rule">Magma Spray deals 2 damage to target creature. If that creature would be put into a graveyard this turn, exile it instead.</rule></rulelist></card><card><name>Manaplasm</name><cost>2G</cost><typelist><type>Creature</type><type>Ooze</type></typelist><pow>1</pow><tgh>1</tgh><rulelist><rule xmlns:xsi="http://www.w3.org/2001/XMLSchema-instance" xsi:type="rule">Whenever you cast a spell, Manaplasm gets +X/+X until end of turn, where X is that spell's converted mana cost.</rule></rulelist></card><card><name>Marble Chalice</name><cost>2W</cost><typelist><type>Artifact</type></typelist><rulelist><rule xmlns:xsi="http://www.w3.org/2001/XMLSchema-instance" xsi:type="rule">{T}: You gain 1 life.</rule></rulelist></card><card><name>Master of Etherium</name><cost>2U</cost><typelist><type>Artifact</type><type>Creature</type><type>Vedalken</type><type>Wizard</type></typelist><pow>*</pow><tgh>*</tgh><rulelist><rule xmlns:xsi="http://www.w3.org/2001/XMLSchema-instance" xsi:type="rule">Master of Etherium's power and toughness are each equal to the number of artifacts you control.</rule><rule xmlns:xsi="http://www.w3.org/2001/XMLSchema-instance" xsi:type="rule">Other artifact creatures you control get +1/+1.</rule></rulelist></card><card><name>Mayael the Anima</name><cost>RGW</cost><typelist><type>Legendary</type><type>Creature</type><type>Elf</type><type>Shaman</type></typelist><pow>2</pow><tgh>3</tgh><rulelist><rule xmlns:xsi="http://www.w3.org/2001/XMLSchema-instance" xsi:type="rule">{3}{R}{G}{W}, {T}: Look at the top five cards of your library. You may put a creature card with power 5 or greater from among them onto the battlefield. Put the rest on the bottom of your library in any order.</rule></rulelist></card><card><name>Metallurgeon</name><cost>1W</cost><typelist><type>Artifact</type><type>Creature</type><type>Human</type><type>Artificer</type></typelist><pow>1</pow><tgh>2</tgh><rulelist><rule xmlns:xsi="http://www.w3.org/2001/XMLSchema-instance" xsi:type="rule">{W}, {T}: Regenerate target artifact.</rule></rulelist></card><card><name>Mighty Emergence</name><cost>2G</cost><typelist><type>Enchantment</type></typelist><rulelist><rule xmlns:xsi="http://www.w3.org/2001/XMLSchema-instance" xsi:type="rule">Whenever a creature with power 5 or greater enters the battlefield under your control, you may put two +1/+1 counters on it.</rule></rulelist></card><card><name>Mindlock Orb</name><cost>3U</cost><typelist><type>Artifact</type></typelist><rulelist><rule xmlns:xsi="http://www.w3.org/2001/XMLSchema-instance" xsi:type="rule">Players can't search libraries.</rule></rulelist></card><card><name>Minion Reflector</name><cost>5</cost><typelist><type>Artifact</type></typelist><rulelist><rule xmlns:xsi="http://www.w3.org/2001/XMLSchema-instance" xsi:type="rule">Whenever a nontoken creature enters the battlefield under your control, you may pay {2}. If you do, put a token that's a copy of that creature onto the battlefield. That token has haste and :At the beginning of the end step, sacrifice this permanent.:</rule></rulelist></card><card><name>Mosstodon</name><cost>4G</cost><typelist><type>Creature</type><type>Plant</type><type>Elephant</type></typelist><pow>5</pow><tgh>3</tgh><rulelist><rule xmlns:xsi="http://www.w3.org/2001/XMLSchema-instance" xsi:type="rule">{1}: Target creature with power 5 or greater gains trample until end of turn.</rule></rulelist></card><card><name>Mountain</name><typelist><type>Basic</type><type>Land</type><type>Mountain</type></typelist><rulelist><rule xmlns:xsi="http://www.w3.org/2001/XMLSchema-instance" xsi:type="rule">R</rule></rulelist></card><card><name>Mountain</name><typelist><type>Basic</type><type>Land</type><type>Mountain</type></typelist><rulelist><rule xmlns:xsi="http://www.w3.org/2001/XMLSchema-instance" xsi:type="rule">R</rule></rulelist></card><card><name>Mountain</name><typelist><type>Basic</type><type>Land</type><type>Mountain</type></typelist><rulelist><rule xmlns:xsi="http://www.w3.org/2001/XMLSchema-instance" xsi:type="rule">R</rule></rulelist></card><card><name>Mountain</name><typelist><type>Basic</type><type>Land</type><type>Mountain</type></typelist><rulelist><rule xmlns:xsi="http://www.w3.org/2001/XMLSchema-instance" xsi:type="rule">R</rule></rulelist></card><card><name>Mycoloth</name><cost>3GG</cost><typelist><type>Creature</type><type>Fungus</type></typelist><pow>4</pow><tgh>4</tgh><rulelist><rule xmlns:xsi="http://www.w3.org/2001/XMLSchema-instance" xsi:type="rule" reminder="As this enters the battlefield, you may sacrifice any number of creatures. This creature enters the battlefield with twice that many +1/+1 counters on it.">Devour 2</rule><rule xmlns:xsi="http://www.w3.org/2001/XMLSchema-instance" xsi:type="rule">the battlefield for each +1/+1 counter on Mycoloth.</rule></rulelist></card><card><name>Naturalize</name><cost>1G</cost><typelist><type>Instant</type></typelist><rulelist><rule xmlns:xsi="http://www.w3.org/2001/XMLSchema-instance" xsi:type="rule">Destroy target artifact or enchantment.</rule></rulelist></card><card><name>Naya Battlemage</name><cost>2G</cost><typelist><type>Creature</type><type>Human</type><type>Shaman</type></typelist><pow>2</pow><tgh>2</tgh><rulelist><rule xmlns:xsi="http://www.w3.org/2001/XMLSchema-instance" xsi:type="rule">{R}, {T}: Target creature gets +2/+0 until end of turn.</rule><rule xmlns:xsi="http://www.w3.org/2001/XMLSchema-instance" xsi:type="rule">{W}, {T}: Tap target creature.</rule></rulelist></card><card><name>Naya Charm</name><cost>RGW</cost><typelist><type>Instant</type></typelist><rulelist><rule xmlns:xsi="http://www.w3.org/2001/XMLSchema-instance" xsi:type="rule">Choose one — Naya Charm deals 3 damage to target creature; or return target card from a graveyard to its owner's hand; or tap all creatures target player controls.</rule></rulelist></card><card><name>Naya Panorama</name><typelist><type>Land</type></typelist><rulelist><rule xmlns:xsi="http://www.w3.org/2001/XMLSchema-instance" xsi:type="rule">{T}: Add {1} to your mana pool.</rule><rule xmlns:xsi="http://www.w3.org/2001/XMLSchema-instance" xsi:type="rule">{1}, {T}, Sacrifice Naya Panorama: Search your library for a basic Mountain, Forest, or Plains card and put it onto the battlefield tapped. Then shuffle your library.</rule></rulelist></card><card><name>Necrogenesis</name><cost>BG</cost><typelist><type>Enchantment</type></typelist><rulelist><rule xmlns:xsi="http://www.w3.org/2001/XMLSchema-instance" xsi:type="rule">{2}: Exile target creature card from a graveyard. Put a 1/1 green Saproling creature token onto the battlefield.</rule></rulelist></card><card><name>Obelisk of Bant</name><cost>3</cost><typelist><type>Artifact</type></typelist><rulelist><rule xmlns:xsi="http://www.w3.org/2001/XMLSchema-instance" xsi:type="rule">{T}: Add {G}, {W}, or {U} to your mana pool.</rule></rulelist></card><card><name>Obelisk of Esper</name><cost>3</cost><typelist><type>Artifact</type></typelist><rulelist><rule xmlns:xsi="http://www.w3.org/2001/XMLSchema-instance" xsi:type="rule">{T}: Add {W}, {U}, or {B} to your mana pool.</rule></rulelist></card><card><name>Obelisk of Jund</name><cost>3</cost><typelist><type>Artifact</type></typelist><rulelist><rule xmlns:xsi="http://www.w3.org/2001/XMLSchema-instance" xsi:type="rule">{T}: Add {B}, {R}, or {G} to your mana pool.</rule></rulelist></card><card><name>Obelisk of Naya</name><cost>3</cost><typelist><type>Artifact</type></typelist><rulelist><rule xmlns:xsi="http://www.w3.org/2001/XMLSchema-instance" xsi:type="rule">{T}: Add {R}, {G}, or {W} to your mana pool.</rule></rulelist></card><card><name>Oblivion Ring</name><cost>2W</cost><typelist><type>Enchantment</type></typelist><rulelist><rule xmlns:xsi="http://www.w3.org/2001/XMLSchema-instance" xsi:type="rule">When Oblivion Ring enters the battlefield, exile another target nonland permanent.</rule><rule xmlns:xsi="http://www.w3.org/2001/XMLSchema-instance" xsi:type="rule"> the battlefield under its owner's control.</rule></rulelist></card><card><name>Onyx Goblet</name><cost>2B</cost><typelist><type>Artifact</type></typelist><rulelist><rule xmlns:xsi="http://www.w3.org/2001/XMLSchema-instance" xsi:type="rule">{T}: Target player loses 1 life.</rule></rulelist></card><card><name>Ooze Garden</name><cost>1G</cost><typelist><type>Enchantment</type></typelist><rulelist><rule xmlns:xsi="http://www.w3.org/2001/XMLSchema-instance" xsi:type="rule">{1}{G}, Sacrifice a non-Ooze creature: Put an X/X green Ooze creature token onto the battlefield, where X is the sacrificed creature's power. Activate this ability only any time you could cast a sorcery.</rule></rulelist></card><card><name>Outrider of Jhess</name><cost>3U</cost><typelist><type>Creature</type><type>Human</type><type>Knight</type></typelist><pow>2</pow><tgh>2</tgh><rulelist><rule xmlns:xsi="http://www.w3.org/2001/XMLSchema-instance" xsi:type="rule" reminder="Whenever a creature you control attacks alone, that creature gets +1/+1 until end of turn.">Exalted</rule></rulelist></card><card><name>Plains</name><typelist><type>Basic</type><type>Land</type><type>Plains</type></typelist><rulelist><rule xmlns:xsi="http://www.w3.org/2001/XMLSchema-instance" xsi:type="rule">W</rule></rulelist></card><card><name>Plains</name><typelist><type>Basic</type><type>Land</type><type>Plains</type></typelist><rulelist><rule xmlns:xsi="http://www.w3.org/2001/XMLSchema-instance" xsi:type="rule">W</rule></rulelist></card><card><name>Plains</name><typelist><type>Basic</type><type>Land</type><type>Plains</type></typelist><rulelist><rule xmlns:xsi="http://www.w3.org/2001/XMLSchema-instance" xsi:type="rule">W</rule></rulelist></card><card><name>Plains</name><typelist><type>Basic</type><type>Land</type><type>Plains</type></typelist><rulelist><rule xmlns:xsi="http://www.w3.org/2001/XMLSchema-instance" xsi:type="rule">W</rule></rulelist></card><card><name>Predator Dragon</name><cost>3RRR</cost><typelist><type>Creature</type><type>Dragon</type></typelist><pow>4</pow><tgh>4</tgh><rulelist><rule xmlns:xsi="http://www.w3.org/2001/XMLSchema-instance" xsi:type="rule">Flying, haste</rule><rule xmlns:xsi="http://www.w3.org/2001/XMLSchema-instance" xsi:type="rule" reminder="As this enters the battlefield, you may sacrifice any number of creatures. This creature enters the battlefield with twice that many +1/+1 counters on it.">Devour 2</rule></rulelist></card><card><name>Prince of Thralls</name><cost>4UBBR</cost><typelist><type>Creature</type><type>Demon</type></typelist><pow>7</pow><tgh>7</tgh><rulelist><rule xmlns:xsi="http://www.w3.org/2001/XMLSchema-instance" xsi:type="rule">Whenever a permanent an opponent controls is put into a graveyard, put that card onto the battlefield under your control unless that opponent pays 3 life.</rule></rulelist></card><card><name>Protomatter Powder</name><cost>2U</cost><typelist><type>Artifact</type></typelist><rulelist><rule xmlns:xsi="http://www.w3.org/2001/XMLSchema-instance" xsi:type="rule">{4}{W}, {T}, Sacrifice Protomatter Powder: Return target artifact card from your graveyard to the battlefield.</rule></rulelist></card><card><name>Punish Ignorance</name><cost>WUUB</cost><typelist><type>Instant</type></typelist><rulelist><rule xmlns:xsi="http://www.w3.org/2001/XMLSchema-instance" xsi:type="rule">Counter target spell. Its controller loses 3 life and you gain 3 life.</rule></rulelist></card><card><name>Puppet Conjurer</name><cost>1B</cost><typelist><type>Artifact</type><type>Creature</type><type>Human</type><type>Wizard</type></typelist><pow>1</pow><tgh>2</tgh><rulelist><rule xmlns:xsi="http://www.w3.org/2001/XMLSchema-instance" xsi:type="rule">{U}, {T}: Put a 0/1 blue Homunculus artifact creature token onto the battlefield.</rule><rule xmlns:xsi="http://www.w3.org/2001/XMLSchema-instance" xsi:type="rule">At the beginning of your upkeep, sacrifice a Homunculus.</rule></rulelist></card><card><name>Qasali Ambusher</name><cost>1GW</cost><typelist><type>Creature</type><type>Cat</type><type>Warrior</type></typelist><pow>2</pow><tgh>3</tgh><rulelist><rule xmlns:xsi="http://www.w3.org/2001/XMLSchema-instance" xsi:type="rule">Reach</rule><rule xmlns:xsi="http://www.w3.org/2001/XMLSchema-instance" xsi:type="rule"> as though it had flash.</rule></rulelist></card><card><name>Quietus Spike</name><cost>3</cost><typelist><type>Artifact</type><type>Equipment</type></typelist><rulelist><rule xmlns:xsi="http://www.w3.org/2001/XMLSchema-instance" xsi:type="rule">Equipped creature has deathtouch.</rule><rule xmlns:xsi="http://www.w3.org/2001/XMLSchema-instance" xsi:type="rule">Whenever equipped creature deals combat damage to a player, that player loses half his or her life, rounded up.</rule><rule xmlns:xsi="http://www.w3.org/2001/XMLSchema-instance" xsi:type="rule">Equip {3}</rule></rulelist></card><card><name>Rafiq of the Many</name><cost>1GWU</cost><typelist><type>Legendary</type><type>Creature</type><type>Human</type><type>Knight</type></typelist><pow>3</pow><tgh>3</tgh><rulelist><rule xmlns:xsi="http://www.w3.org/2001/XMLSchema-instance" xsi:type="rule" reminder="Whenever a creature you control attacks alone, that creature gets +1/+1 until end of turn.">Exalted</rule><rule xmlns:xsi="http://www.w3.org/2001/XMLSchema-instance" xsi:type="rule">e you control attacks alone, it gains double strike until end of turn.</rule></rulelist></card><card><name>Rakeclaw Gargantuan</name><cost>2RGW</cost><typelist><type>Creature</type><type>Beast</type></typelist><pow>5</pow><tgh>3</tgh><rulelist><rule xmlns:xsi="http://www.w3.org/2001/XMLSchema-instance" xsi:type="rule">reater gains first strike until end of turn.</rule></rulelist></card><card><name>Ranger of Eos</name><cost>3W</cost><typelist><type>Creature</type><type>Human</type><type>Soldier</type></typelist><pow>3</pow><tgh>2</tgh><rulelist><rule xmlns:xsi="http://www.w3.org/2001/XMLSchema-instance" xsi:type="rule">When Ranger of Eos enters the battlefield, you may search your library for up to two creature cards with converted mana cost 1 or less, reveal them, and put them into your hand. If you do, shuffle your library.</rule></rulelist></card><card><name>Realm Razer</name><cost>3RGW</cost><typelist><type>Creature</type><type>Beast</type></typelist><pow>4</pow><tgh>2</tgh><rulelist><rule xmlns:xsi="http://www.w3.org/2001/XMLSchema-instance" xsi:type="rule">When Realm Razer enters the battlefield, exile all lands.</rule><rule xmlns:xsi="http://www.w3.org/2001/XMLSchema-instance" xsi:type="rule">When Realm Razer leaves the battlefield, return the exiled cards to the battlefield tapped under their owners' control.</rule></rulelist></card><card><name>Relic of Progenitus</name><cost>1</cost><typelist><type>Artifact</type></typelist><rulelist><rule xmlns:xsi="http://www.w3.org/2001/XMLSchema-instance" xsi:type="rule">{T}: Target player exiles a card from his or her graveyard.</rule><rule xmlns:xsi="http://www.w3.org/2001/XMLSchema-instance" xsi:type="rule">le Relic of Progenitus: Exile all cards from all graveyards. Draw a card.</rule></rulelist></card><card><name>Resounding Roar</name><cost>1G</cost><typelist><type>Instant</type></typelist><rulelist><rule xmlns:xsi="http://www.w3.org/2001/XMLSchema-instance" xsi:type="rule">Target creature gets +3/+3 until end of turn.</rule><rule xmlns:xsi="http://www.w3.org/2001/XMLSchema-instance" xsi:type="rule" reminder="{5}{R}{G}{W}, Discard this card: Draw a card.">Cycling {5}{R}{G}{W}</rule><rule xmlns:xsi="http://www.w3.org/2001/XMLSchema-instance" xsi:type="rule">When you cycle Resounding Roar, target creature gets +6/+6 until end of turn.</rule></rulelist></card><card><name>Resounding Scream</name><cost>2B</cost><typelist><type>Sorcery</type></typelist><rulelist><rule xmlns:xsi="http://www.w3.org/2001/XMLSchema-instance" xsi:type="rule">Target player discards a card at random.</rule><rule xmlns:xsi="http://www.w3.org/2001/XMLSchema-instance" xsi:type="rule" reminder="{5}{U}{B}{R}, Discard this card: Draw a card.">Cycling {5}{U}{B}{R}</rule><rule xmlns:xsi="http://www.w3.org/2001/XMLSchema-instance" xsi:type="rule">When you cycle Resounding Scream, target player discards two cards at random.</rule></rulelist></card><card><name>Resounding Silence</name><cost>3W</cost><typelist><type>Instant</type></typelist><rulelist><rule xmlns:xsi="http://www.w3.org/2001/XMLSchema-instance" xsi:type="rule">Exile target attacking creature.</rule><rule xmlns:xsi="http://www.w3.org/2001/XMLSchema-instance" xsi:type="rule" reminder="{5}{G}{W}{U}, Discard this card: Draw a card.">Cycling {5}{G}{W}{U}</rule><rule xmlns:xsi="http://www.w3.org/2001/XMLSchema-instance" xsi:type="rule">When you cycle Resounding Silence, exile up to two target attacking creatures.</rule></rulelist></card><card><name>Resounding Thunder</name><cost>2R</cost><typelist><type>Instant</type></typelist><rulelist><rule xmlns:xsi="http://www.w3.org/2001/XMLSchema-instance" xsi:type="rule">Resounding Thunder deals 3 damage to target creature or player.</rule><rule xmlns:xsi="http://www.w3.org/2001/XMLSchema-instance" xsi:type="rule" reminder="{5}{B}{R}{G}, Discard this card: Draw a card.">Cycling {5}{B}{R}{G}</rule><rule xmlns:xsi="http://www.w3.org/2001/XMLSchema-instance" xsi:type="rule">When you cycle Resounding Thunder, it deals 6 damage to target creature or player.</rule></rulelist></card><card><name>Resounding Wave</name><cost>2U</cost><typelist><type>Instant</type></typelist><rulelist><rule xmlns:xsi="http://www.w3.org/2001/XMLSchema-instance" xsi:type="rule">Return target permanent to its owner's hand.</rule><rule xmlns:xsi="http://www.w3.org/2001/XMLSchema-instance" xsi:type="rule" reminder="{5}{W}{U}{B}, Discard this card: Draw a card.">Cycling {5}{W}{U}{B}</rule><rule xmlns:xsi="http://www.w3.org/2001/XMLSchema-instance" xsi:type="rule">When you cycle Resounding Wave, return two target permanents to their owners' hands.</rule></rulelist></card><card><name>Rhox Charger</name><cost>3G</cost><typelist><type>Creature</type><type>Rhino</type><type>Soldier</type></typelist><pow>3</pow><tgh>3</tgh><rulelist><rule xmlns:xsi="http://www.w3.org/2001/XMLSchema-instance" xsi:type="rule">Trample</rule><rule xmlns:xsi="http://www.w3.org/2001/XMLSchema-instance" xsi:type="rule" reminder="Whenever a creature you control attacks alone, that creature gets +1/+1 until end of turn.">Exalted</rule></rulelist></card><card><name>Rhox War Monk</name><cost>GWU</cost><typelist><type>Creature</type><type>Rhino</type><type>Monk</type></typelist><pow>3</pow><tgh>4</tgh><rulelist><rule xmlns:xsi="http://www.w3.org/2001/XMLSchema-instance" xsi:type="rule">Lifelink</rule></rulelist></card><card><name>Ridge Rannet</name><cost>5RR</cost><typelist><type>Creature</type><type>Beast</type></typelist><pow>6</pow><tgh>4</tgh><rulelist><rule xmlns:xsi="http://www.w3.org/2001/XMLSchema-instance" xsi:type="rule" reminder="{2}, Discard this card: Draw a card.">Cycling {2}</rule></rulelist></card><card><name>Rip-Clan Crasher</name><cost>RG</cost><typelist><type>Creature</type><type>Human</type><type>Warrior</type></typelist><pow>2</pow><tgh>2</tgh><rulelist><rule xmlns:xsi="http://www.w3.org/2001/XMLSchema-instance" xsi:type="rule">Haste</rule></rulelist></card><card><name>Rockcaster Platoon</name><cost>5WW</cost><typelist><type>Creature</type><type>Rhino</type><type>Soldier</type></typelist><pow>5</pow><tgh>7</tgh><rulelist><rule xmlns:xsi="http://www.w3.org/2001/XMLSchema-instance" xsi:type="rule">{4}{G}: Rockcaster Platoon deals 2 damage to each creature with flying and each player.</rule></rulelist></card><card><name>Rockslide Elemental</name><cost>2R</cost><typelist><type>Creature</type><type>Elemental</type></typelist><pow>1</pow><tgh>1</tgh><rulelist><rule xmlns:xsi="http://www.w3.org/2001/XMLSchema-instance" xsi:type="rule">First strike</rule><rule xmlns:xsi="http://www.w3.org/2001/XMLSchema-instance" xsi:type="rule">Whenever another creature is put into a graveyard from the battlefield, you may put a +1/+1 counter on Rockslide Elemental.</rule></rulelist></card><card><name>Sacellum Godspeaker</name><cost>2G</cost><typelist><type>Creature</type><type>Elf</type><type>Druid</type></typelist><pow>2</pow><tgh>2</tgh><rulelist><rule xmlns:xsi="http://www.w3.org/2001/XMLSchema-instance" xsi:type="rule">{T}: Reveal any number of creature cards with power 5 or greater from your hand. Add {G} to your mana pool for each card revealed this way.</rule></rulelist></card><card><name>Salvage Titan</name><cost>4BB</cost><typelist><type>Artifact</type><type>Creature</type><type>Golem</type></typelist><pow>6</pow><tgh>4</tgh><rulelist><rule xmlns:xsi="http://www.w3.org/2001/XMLSchema-instance" xsi:type="rule">You may sacrifice three artifacts rather than pay Salvage Titan's mana cost.</rule><rule xmlns:xsi="http://www.w3.org/2001/XMLSchema-instance" xsi:type="rule">Exile three artifact cards from your graveyard: Return Salvage Titan from your graveyard to your hand.</rule></rulelist></card><card><name>Sanctum Gargoyle</name><cost>3W</cost><typelist><type>Artifact</type><type>Creature</type><type>Gargoyle</type></typelist><pow>2</pow><tgh>3</tgh><rulelist><rule xmlns:xsi="http://www.w3.org/2001/XMLSchema-instance" xsi:type="rule">Flying</rule><rule xmlns:xsi="http://www.w3.org/2001/XMLSchema-instance" xsi:type="rule">When Sanctum Gargoyle enters the battlefield, you may return target artifact card from your graveyard to your hand.</rule></rulelist></card><card><name>Sangrite Surge</name><cost>4RG</cost><typelist><type>Sorcery</type></typelist><rulelist><rule xmlns:xsi="http://www.w3.org/2001/XMLSchema-instance" xsi:type="rule">Target creature gets +3/+3 and gains double strike until end of turn.</rule></rulelist></card><card><name>Sarkhan Vol</name><cost>2RG</cost><loyalty>4</loyalty><typelist><type>Planeswalker</type><type>Sarkhan</type></typelist><rulelist><rule xmlns:xsi="http://www.w3.org/2001/XMLSchema-instance" xsi:type="rule">+1: Creatures you control get +1/+1 and gain haste until end of turn.</rule><rule xmlns:xsi="http://www.w3.org/2001/XMLSchema-instance" xsi:type="rule">-2: Gain control of target creature until end of turn. Untap that creature. It gains haste until end of turn.</rule><rule xmlns:xsi="http://www.w3.org/2001/XMLSchema-instance" xsi:type="rule">ve 4/4 red Dragon creature tokens with flying onto the battlefield.</rule></rulelist></card><card><name>Savage Hunger</name><cost>2G</cost><typelist><type>Enchantment</type><type>Aura</type></typelist><rulelist><rule xmlns:xsi="http://www.w3.org/2001/XMLSchema-instance" xsi:type="rule">Enchant creature</rule><rule xmlns:xsi="http://www.w3.org/2001/XMLSchema-instance" xsi:type="rule">Enchanted creature gets +1/+0 and has trample.</rule><rule xmlns:xsi="http://www.w3.org/2001/XMLSchema-instance" xsi:type="rule" reminder="{2}, Discard this card: Draw a card.">Cycling {2}</rule></rulelist></card><card><name>Savage Lands</name><typelist><type>Land</type></typelist><rulelist><rule xmlns:xsi="http://www.w3.org/2001/XMLSchema-instance" xsi:type="rule">Savage Lands enters the battlefield tapped.</rule><rule xmlns:xsi="http://www.w3.org/2001/XMLSchema-instance" xsi:type="rule">{T}: Add {B}, {R}, or {G} to your mana pool.</rule></rulelist></card><card><name>Scavenger Drake</name><cost>3B</cost><typelist><type>Creature</type><type>Drake</type></typelist><pow>1</pow><tgh>1</tgh><rulelist><rule xmlns:xsi="http://www.w3.org/2001/XMLSchema-instance" xsi:type="rule">Flying</rule><rule xmlns:xsi="http://www.w3.org/2001/XMLSchema-instance" xsi:type="rule">Whenever another creature is put into a graveyard from the battlefield, you may put a +1/+1 counter on Scavenger Drake.</rule></rulelist></card><card><name>Scourge Devil</name><cost>4R</cost><typelist><type>Creature</type><type>Devil</type></typelist><pow>3</pow><tgh>3</tgh><rulelist><rule xmlns:xsi="http://www.w3.org/2001/XMLSchema-instance" xsi:type="rule">When Scourge Devil enters the battlefield, creatures you control get +1/+0 until end of turn.</rule><rule xmlns:xsi="http://www.w3.org/2001/XMLSchema-instance" xsi:type="rule" reminder="{2}{R}: Return this card from your graveyard to the battlefield. It gains haste. Exile it at the beginning of the next end step or if it would leave the battlefield. Unearth only as a sorcery.">Unearth {2}{R}</rule></rulelist></card><card><name>Scourglass</name><cost>3WW</cost><typelist><type>Artifact</type></typelist><rulelist><rule xmlns:xsi="http://www.w3.org/2001/XMLSchema-instance" xsi:type="rule">{T}, Sacrifice Scourglass: Destroy all permanents except for artifacts and lands. Activate this ability only during your upkeep.</rule></rulelist></card><card><name>Seaside Citadel</name><typelist><type>Land</type></typelist><rulelist><rule xmlns:xsi="http://www.w3.org/2001/XMLSchema-instance" xsi:type="rule">Seaside Citadel enters the battlefield tapped.</rule><rule xmlns:xsi="http://www.w3.org/2001/XMLSchema-instance" xsi:type="rule">{T}: Add {G}, {W}, or {U} to your mana pool.</rule></rulelist></card><card><name>Sedraxis Specter</name><cost>UBR</cost><typelist><type>Creature</type><type>Specter</type></typelist><pow>3</pow><tgh>2</tgh><rulelist><rule xmlns:xsi="http://www.w3.org/2001/XMLSchema-instance" xsi:type="rule">Flying</rule><rule xmlns:xsi="http://www.w3.org/2001/XMLSchema-instance" xsi:type="rule">Whenever Sedraxis Specter deals combat damage to a player, that player discards a card.</rule><rule xmlns:xsi="http://www.w3.org/2001/XMLSchema-instance" xsi:type="rule" reminder="{1}{B}: Return this card from your graveyard to the battlefield. It gains haste. Exile it at the beginning of the next end step or if it would leave the battlefield. Unearth only as a sorcery.">Unearth {1}{B}</rule></rulelist></card><card><name>Sedris, the Traitor King</name><cost>3UBR</cost><typelist><type>Legendary</type><type>Creature</type><type>Zombie</type><type>Warrior</type></typelist><pow>5</pow><tgh>5</tgh><rulelist><rule xmlns:xsi="http://www.w3.org/2001/XMLSchema-instance" xsi:type="rule" reminder="{2}{B}: Return the card to the battlefield. The creature gains haste. Exile it at the beginning of the next end step or if it would leave the battlefield. Unearth only as a sorcery.">Each creature card in your graveyard has unearth {2}{B}.</rule></rulelist></card><card><name>Shadowfeed</name><cost>B</cost><typelist><type>Instant</type></typelist><rulelist><rule xmlns:xsi="http://www.w3.org/2001/XMLSchema-instance" xsi:type="rule">Exile target card from a graveyard. You gain 3 life.</rule></rulelist></card><card><name>Sharding Sphinx</name><cost>4UU</cost><typelist><type>Artifact</type><type>Creature</type><type>Sphinx</type></typelist><pow>4</pow><tgh>4</tgh><rulelist><rule xmlns:xsi="http://www.w3.org/2001/XMLSchema-instance" xsi:type="rule">Flying</rule><rule xmlns:xsi="http://www.w3.org/2001/XMLSchema-instance" xsi:type="rule">Whenever an artifact creature you control deals combat damage to a player, you may put a 1/1 blue Thopter artifact creature token with flying onto the battlefield.</rule></rulelist></card><card><name>Sharuum the Hegemon</name><cost>3WUB</cost><typelist><type>Legendary</type><type>Artifact</type><type>Creature</type><type>Sphinx</type></typelist><pow>5</pow><tgh>5</tgh><rulelist><rule xmlns:xsi="http://www.w3.org/2001/XMLSchema-instance" xsi:type="rule">Flying</rule><rule xmlns:xsi="http://www.w3.org/2001/XMLSchema-instance" xsi:type="rule">e Hegemon enters the battlefield, you may return target artifact card from your graveyard to the battlefield.</rule></rulelist></card><card><name>Shore Snapper</name><cost>2B</cost><typelist><type>Creature</type><type>Beast</type></typelist><pow>2</pow><tgh>2</tgh><rulelist><rule xmlns:xsi="http://www.w3.org/2001/XMLSchema-instance" xsi:type="rule">{U}: Shore Snapper gains islandwalk until end of turn.</rule></rulelist></card><card><name>Sighted-Caste Sorcerer</name><cost>1W</cost><typelist><type>Creature</type><type>Human</type><type>Wizard</type></typelist><pow>1</pow><tgh>1</tgh><rulelist><rule xmlns:xsi="http://www.w3.org/2001/XMLSchema-instance" xsi:type="rule" reminder="Whenever a creature you control attacks alone, that creature gets +1/+1 until end of turn.">Exalted</rule><rule xmlns:xsi="http://www.w3.org/2001/XMLSchema-instance" xsi:type="rule" reminder="It can't be the target of spells or abilities.">{U}: Sighted-Caste Sorcerer gains shroud until end of turn.</rule></rulelist></card><card><name>Sigil Blessing</name><cost>GW</cost><typelist><type>Instant</type></typelist><rulelist><rule xmlns:xsi="http://www.w3.org/2001/XMLSchema-instance" xsi:type="rule">Until end of turn, target creature you control gets +3/+3 and other creatures you control get +1/+1.</rule></rulelist></card><card><name>Sigil of Distinction</name><cost>X</cost><typelist><type>Artifact</type><type>Equipment</type></typelist><rulelist><rule xmlns:xsi="http://www.w3.org/2001/XMLSchema-instance" xsi:type="rule">Sigil of Distinction enters the battlefield with X charge counters on it.</rule><rule xmlns:xsi="http://www.w3.org/2001/XMLSchema-instance" xsi:type="rule">Equipped creature gets +1/+1 for each charge counter on Sigil of Distinction.</rule><rule xmlns:xsi="http://www.w3.org/2001/XMLSchema-instance" xsi:type="rule">nction.</rule></rulelist></card><card><name>Sigiled Paladin</name><cost>WW</cost><typelist><type>Creature</type><type>Human</type><type>Knight</type></typelist><pow>2</pow><tgh>2</tgh><rulelist><rule xmlns:xsi="http://www.w3.org/2001/XMLSchema-instance" xsi:type="rule">First strike</rule><rule xmlns:xsi="http://www.w3.org/2001/XMLSchema-instance" xsi:type="rule" reminder="Whenever a creature you control attacks alone, that creature gets +1/+1 until end of turn.">Exalted</rule></rulelist></card><card><name>Skeletal Kathari</name><cost>4B</cost><typelist><type>Creature</type><type>Bird</type><type>Skeleton</type></typelist><pow>3</pow><tgh>2</tgh><rulelist><rule xmlns:xsi="http://www.w3.org/2001/XMLSchema-instance" xsi:type="rule">Flying</rule><rule xmlns:xsi="http://www.w3.org/2001/XMLSchema-instance" xsi:type="rule">{B}, Sacrifice a creature: Regenerate Skeletal Kathari.</rule></rulelist></card><card><name>Skeletonize</name><cost>4R</cost><typelist><type>Instant</type></typelist><rulelist><rule xmlns:xsi="http://www.w3.org/2001/XMLSchema-instance" xsi:type="rule">Skeletonize deals 3 damage to target creature. When a creature dealt damage this way is put into a graveyard this turn, put a 1/1 black Skeleton creature token onto the battlefield with :{B}: Regenerate this creature.:</rule></rulelist></card><card><name>Skill Borrower</name><cost>2U</cost><typelist><type>Artifact</type><type>Creature</type><type>Human</type><type>Wizard</type></typelist><pow>1</pow><tgh>3</tgh><rulelist><rule xmlns:xsi="http://www.w3.org/2001/XMLSchema-instance" xsi:type="rule">Play with the top card of your library revealed.</rule><rule xmlns:xsi="http://www.w3.org/2001/XMLSchema-instance" xsi:type="rule" reminder="If any of the abilities use that card's name, use this creature's name instead.">As long as the top card of your library is an artifact or creature card, Skill Borrower has all activated abilities of that card.</rule></rulelist></card><card><name>Skullmulcher</name><cost>4G</cost><typelist><type>Creature</type><type>Elemental</type></typelist><pow>3</pow><tgh>3</tgh><rulelist><rule xmlns:xsi="http://www.w3.org/2001/XMLSchema-instance" xsi:type="rule" reminder="As this enters the battlefield, you may sacrifice any number of creatures. This creature enters the battlefield with that many +1/+1 counters on it.">Devour 1</rule><rule xmlns:xsi="http://www.w3.org/2001/XMLSchema-instance" xsi:type="rule">When Skullmulcher enters the battlefield, draw a card for each creature it devoured.</rule></rulelist></card><card><name>Soul's Fire</name><cost>2R</cost><typelist><type>Instant</type></typelist><rulelist><rule xmlns:xsi="http://www.w3.org/2001/XMLSchema-instance" xsi:type="rule">Target creature you control on the battlefield deals damage equal to its power to target creature or player.</rule></rulelist></card><card><name>Soul's Grace</name><cost>1W</cost><typelist><type>Instant</type></typelist><rulelist><rule xmlns:xsi="http://www.w3.org/2001/XMLSchema-instance" xsi:type="rule">You gain life equal to target creature's power.</rule></rulelist></card><card><name>Soul's Might</name><cost>4G</cost><typelist><type>Sorcery</type></typelist><rulelist><rule xmlns:xsi="http://www.w3.org/2001/XMLSchema-instance" xsi:type="rule">Put X +1/+1 counters on target creature, where X is that creature's power.</rule></rulelist></card><card><name>Spearbreaker Behemoth</name><cost>5GG</cost><typelist><type>Creature</type><type>Beast</type></typelist><pow>5</pow><tgh>5</tgh><rulelist><rule xmlns:xsi="http://www.w3.org/2001/XMLSchema-instance" xsi:type="rule">Spearbreaker Behemoth is indestructible.</rule><rule xmlns:xsi="http://www.w3.org/2001/XMLSchema-instance" xsi:type="rule">{1}: Target creature with power 5 or greater is indestructible this turn.</rule></rulelist></card><card><name>Spell Snip</name><cost>2U</cost><typelist><type>Instant</type></typelist><rulelist><rule xmlns:xsi="http://www.w3.org/2001/XMLSchema-instance" xsi:type="rule">Counter target spell unless its controller pays {1}.</rule><rule xmlns:xsi="http://www.w3.org/2001/XMLSchema-instance" xsi:type="rule" reminder="{2}, Discard this card: Draw a card.">Cycling {2}</rule></rulelist></card><card><name>Sphinx Sovereign</name><cost>4WUUB</cost><typelist><type>Artifact</type><type>Creature</type><type>Sphinx</type></typelist><pow>6</pow><tgh>6</tgh><rulelist><rule xmlns:xsi="http://www.w3.org/2001/XMLSchema-instance" xsi:type="rule">Flying</rule><rule xmlns:xsi="http://www.w3.org/2001/XMLSchema-instance" xsi:type="rule">At the beginning of your end step, you gain 3 life if Sphinx Sovereign is untapped. Otherwise, each opponent loses 3 life.</rule></rulelist></card><card><name>Sphinx's Herald</name><cost>U</cost><typelist><type>Artifact</type><type>Creature</type><type>Vedalken</type><type>d</type></typelist><pow>1</pow><tgh>1</tgh><rulelist><rule xmlns:xsi="http://www.w3.org/2001/XMLSchema-instance" xsi:type="rule">{2}{U}, {T}, Sacrifice a white creature, a blue creature, and a black creature: Search your library for a card named Sphinx Sovereign and put it onto the battlefield. Then shuffle your library.</rule></rulelist></card><card><name>Sprouting Thrinax</name><cost>BRG</cost><typelist><type>Creature</type><type>Lizard</type></typelist><pow>3</pow><tgh>3</tgh><rulelist><rule xmlns:xsi="http://www.w3.org/2001/XMLSchema-instance" xsi:type="rule">When Sprouting Thrinax is put into a graveyard from the battlefield, put three 1/1 green Saproling creature tokens onto the battlefield.</rule></rulelist></card><card><name>Steelclad Serpent</name><cost>5U</cost><typelist><type>Artifact</type><type>Creature</type><type>Serpent</type></typelist><pow>4</pow><tgh>5</tgh><rulelist><rule xmlns:xsi="http://www.w3.org/2001/XMLSchema-instance" xsi:type="rule">Steelclad Serpent can't attack unless you control another artifact.</rule></rulelist></card><card><name>Steward of Valeron</name><cost>GW</cost><typelist><type>Creature</type><type>Human</type><type>Druid</type><type>Knight</type></typelist><pow>2</pow><tgh>2</tgh><rulelist><rule xmlns:xsi="http://www.w3.org/2001/XMLSchema-instance" xsi:type="rule">Vigilance</rule><rule xmlns:xsi="http://www.w3.org/2001/XMLSchema-instance" xsi:type="rule">{T}: Add {G} to your mana pool.</rule></rulelist></card><card><name>Stoic Angel</name><cost>1GWU</cost><typelist><type>Creature</type><type>Angel</type></typelist><pow>3</pow><tgh>4</tgh><rulelist><rule xmlns:xsi="http://www.w3.org/2001/XMLSchema-instance" xsi:type="rule">Flying, vigilance</rule><rule xmlns:xsi="http://www.w3.org/2001/XMLSchema-instance" xsi:type="rule">Players can't untap more than one creature during their untap steps.</rule></rulelist></card><card><name>Sunseed Nurturer</name><cost>2W</cost><typelist><type>Creature</type><type>Human</type><type>Druid</type><type>Wizard</type></typelist><pow>1</pow><tgh>1</tgh><rulelist><rule xmlns:xsi="http://www.w3.org/2001/XMLSchema-instance" xsi:type="rule">At the beginning of your end step, if you control a creature with power 5 or greater, you may gain 2 life.</rule><rule xmlns:xsi="http://www.w3.org/2001/XMLSchema-instance" xsi:type="rule">{T}: Add {1} to your mana pool.</rule></rulelist></card><card><name>Swamp</name><typelist><type>Basic</type><type>Land</type><type>Swamp</type></typelist><rulelist><rule xmlns:xsi="http://www.w3.org/2001/XMLSchema-instance" xsi:type="rule">B</rule></rulelist></card><card><name>Swamp</name><typelist><type>Basic</type><type>Land</type><type>Swamp</type></typelist><rulelist><rule xmlns:xsi="http://www.w3.org/2001/XMLSchema-instance" xsi:type="rule">B</rule></rulelist></card><card><name>Swamp</name><typelist><type>Basic</type><type>Land</type><type>Swamp</type></typelist><rulelist><rule xmlns:xsi="http://www.w3.org/2001/XMLSchema-instance" xsi:type="rule">B</rule></rulelist></card><card><name>Swamp</name><typelist><type>Basic</type><type>Land</type><type>Swamp</type></typelist><rulelist><rule xmlns:xsi="http://www.w3.org/2001/XMLSchema-instance" xsi:type="rule">B</rule></rulelist></card><card><name>Swerve</name><cost>UR</cost><typelist><type>Instant</type></typelist><rulelist><rule xmlns:xsi="http://www.w3.org/2001/XMLSchema-instance" xsi:type="rule">Change the target of target spell with a single target.</rule></rulelist></card><card><name>Tar Fiend</name><cost>5B</cost><typelist><type>Creature</type><type>Elemental</type></typelist><pow>4</pow><tgh>4</tgh><rulelist><rule xmlns:xsi="http://www.w3.org/2001/XMLSchema-instance" xsi:type="rule" reminder="As this enters the battlefield, you may sacrifice any number of creatures. This creature enters the battlefield with twice that many +1/+1 counters on it.">Devour 2</rule><rule xmlns:xsi="http://www.w3.org/2001/XMLSchema-instance" xsi:type="rule">When Tar Fiend enters the battlefield, target player discards a card for each creature it devoured.</rule></rulelist></card><card><name>Tezzeret the Seeker</name><cost>3UU</cost><loyalty>4</loyalty><typelist><type>Planeswalker</type><type>Tezzeret</type></typelist><rulelist><rule xmlns:xsi="http://www.w3.org/2001/XMLSchema-instance" xsi:type="rule">+1: Untap up to two target artifacts.</rule><rule xmlns:xsi="http://www.w3.org/2001/XMLSchema-instance" xsi:type="rule">-X: Search your library for an artifact card with converted mana cost X or less and put it onto the battlefield. Then shuffle your library.</rule><rule xmlns:xsi="http://www.w3.org/2001/XMLSchema-instance" xsi:type="rule">-5: Artifacts you control become 5/5 artifact creatures until end of turn.</rule></rulelist></card><card><name>Thorn-Thrash Viashino</name><cost>3R</cost><typelist><type>Creature</type><type>Viashino</type><type>Warrior</type></typelist><pow>2</pow><tgh>2</tgh><rulelist><rule xmlns:xsi="http://www.w3.org/2001/XMLSchema-instance" xsi:type="rule" reminder="As this enters the battlefield, you may sacrifice any number of creatures. This creature enters the battlefield with twice that many +1/+1 counters on it.">Devour 2</rule><rule xmlns:xsi="http://www.w3.org/2001/XMLSchema-instance" xsi:type="rule">{G}: Thorn-Thrash Viashino gains trample until end of turn.</rule></rulelist></card><card><name>Thoughtcutter Agent</name><cost>UB</cost><typelist><type>Artifact</type><type>Creature</type><type>Human</type><type>Rogue</type></typelist><pow>1</pow><tgh>1</tgh><rulelist><rule xmlns:xsi="http://www.w3.org/2001/XMLSchema-instance" xsi:type="rule">{U}{B}, {T}: Target player loses 1 life and reveals his or her hand.</rule></rulelist></card><card><name>Thunder-Thrash Elder</name><cost>2R</cost><typelist><type>Creature</type><type>Viashino</type><type>Warrior</type></typelist><pow>1</pow><tgh>1</tgh><rulelist><rule xmlns:xsi="http://www.w3.org/2001/XMLSchema-instance" xsi:type="rule" reminder="As this enters the battlefield, you may sacrifice any number of creatures. This creature enters the battlefield with three times that many +1/+1 counters on it.">Devour 3</rule></rulelist></card><card><name>Tidehollow Sculler</name><cost>WB</cost><typelist><type>Artifact</type><type>Creature</type><type>Zombie</type></typelist><pow>2</pow><tgh>2</tgh><rulelist><rule xmlns:xsi="http://www.w3.org/2001/XMLSchema-instance" xsi:type="rule">When Tidehollow Sculler enters the battlefield, target opponent reveals his or her hand and you choose a nonland card from it. Exile that card.</rule><rule xmlns:xsi="http://www.w3.org/2001/XMLSchema-instance" xsi:type="rule">When Tidehollow Sculler leaves the battlefield, return the exiled card to its owner's hand.</rule></rulelist></card><card><name>Tidehollow Strix</name><cost>UB</cost><typelist><type>Artifact</type><type>Creature</type><type>Bird</type></typelist><pow>2</pow><tgh>1</tgh><rulelist><rule xmlns:xsi="http://www.w3.org/2001/XMLSchema-instance" xsi:type="rule">Flying</rule><rule xmlns:xsi="http://www.w3.org/2001/XMLSchema-instance" xsi:type="rule" reminder="Any amount of damage this deals to a creature is enough to destroy it.">Deathtouch</rule></rulelist></card><card><name>Titanic Ultimatum</name><cost>RRGGGWW</cost><typelist><type>Sorcery</type></typelist><rulelist><rule xmlns:xsi="http://www.w3.org/2001/XMLSchema-instance" xsi:type="rule">Until end of turn, creatures you control get +5/+5 and gain first strike, lifelink, and trample.</rule></rulelist></card><card><name>Topan Ascetic</name><cost>2G</cost><typelist><type>Creature</type><type>Human</type><type>Monk</type></typelist><pow>2</pow><tgh>2</tgh><rulelist><rule xmlns:xsi="http://www.w3.org/2001/XMLSchema-instance" xsi:type="rule">Tap an untapped creature you control: Topan Ascetic gets +1/+1 until end of turn.</rule></rulelist></card><card><name>Tortoise Formation</name><cost>3U</cost><typelist><type>Instant</type></typelist><rulelist><rule xmlns:xsi="http://www.w3.org/2001/XMLSchema-instance" xsi:type="rule" reminder="They can't be the targets of spells or abilities.">Creatures you control gain shroud until end of turn.</rule></rulelist></card><card><name>Tower Gargoyle</name><cost>1WUB</cost><typelist><type>Artifact</type><type>Creature</type><type>Gargoyle</type></typelist><pow>4</pow><tgh>4</tgh><rulelist><rule xmlns:xsi="http://www.w3.org/2001/XMLSchema-instance" xsi:type="rule">Flying</rule></rulelist></card><card><name>Undead Leotau</name><cost>5B</cost><typelist><type>Creature</type><type>Zombie</type><type>Cat</type></typelist><pow>3</pow><tgh>4</tgh><rulelist><rule xmlns:xsi="http://www.w3.org/2001/XMLSchema-instance" xsi:type="rule">{R}: Undead Leotau gets +1/-1 until end of turn.</rule><rule xmlns:xsi="http://www.w3.org/2001/XMLSchema-instance" xsi:type="rule" reminder="{2}{B}: Return this card from your graveyard to the battlefield. It gains haste. Exile it at the beginning of the next end step or if it would leave the battlefield. Unearth only as a sorcery.">Unearth {2}{B}</rule></rulelist></card><card><name>Vectis Silencers</name><cost>2U</cost><typelist><type>Artifact</type><type>Creature</type><type>Human</type><type>Rogue</type></typelist><pow>1</pow><tgh>2</tgh><rulelist><rule xmlns:xsi="http://www.w3.org/2001/XMLSchema-instance" xsi:type="rule" reminder="Any amount of damage it deals to a creature is enough to destroy that creature.">{2}{B}: Vectis Silencers gains deathtouch until end of turn.</rule></rulelist></card><card><name>Vein Drinker</name><cost>4BB</cost><typelist><type>Creature</type><type>Vampire</type></typelist><pow>4</pow><tgh>4</tgh><rulelist><rule xmlns:xsi="http://www.w3.org/2001/XMLSchema-instance" xsi:type="rule">Flying</rule><rule xmlns:xsi="http://www.w3.org/2001/XMLSchema-instance" xsi:type="rule">{R}, {T}: Vein Drinker deals damage equal to its power to target creature. That creature deals damage equal to its power to Vein Drinker.</rule><rule xmlns:xsi="http://www.w3.org/2001/XMLSchema-instance" xsi:type="rule">Whenever a creature dealt damage by Vein Drinker this turn is put into a graveyard, put a +1/+1 counter on Vein Drinker.</rule></rulelist></card><card><name>Viashino Skeleton</name><cost>3R</cost><typelist><type>Creature</type><type>Viashino</type><type>Skeleton</type></typelist><pow>2</pow><tgh>1</tgh><rulelist><rule xmlns:xsi="http://www.w3.org/2001/XMLSchema-instance" xsi:type="rule">{1}{B}, Discard a card: Regenerate Viashino Skeleton.</rule></rulelist></card><card><name>Vicious Shadows</name><cost>6R</cost><typelist><type>Enchantment</type></typelist><rulelist><rule xmlns:xsi="http://www.w3.org/2001/XMLSchema-instance" xsi:type="rule">Whenever a creature is put into a graveyard from the battlefield, you may have Vicious Shadows deal damage to target player equal to the number of cards in that player's hand.</rule></rulelist></card><card><name>Violent Ultimatum</name><cost>BBRRRGG</cost><typelist><type>Sorcery</type></typelist><rulelist><rule xmlns:xsi="http://www.w3.org/2001/XMLSchema-instance" xsi:type="rule">Destroy three target permanents.</rule></rulelist></card><card><name>Viscera Dragger</name><cost>3B</cost><typelist><type>Creature</type><type>Zombie</type><type>Ogre</type><type>Warrior</type></typelist><pow>3</pow><tgh>3</tgh><rulelist><rule xmlns:xsi="http://www.w3.org/2001/XMLSchema-instance" xsi:type="rule" reminder="{2}, Discard this card: Draw a card.">Cycling {2}</rule><rule xmlns:xsi="http://www.w3.org/2001/XMLSchema-instance" xsi:type="rule" reminder="{1}{B}: Return this card from your graveyard to the battlefield. It gains haste. Exile it at the beginning of the next end step or if it would leave the battlefield. Unearth only as a sorcery.">Unearth {1}{B}</rule></rulelist></card><card><name>Vithian Stinger</name><cost>2R</cost><typelist><type>Creature</type><type>Human</type><type>Shaman</type></typelist><pow>0</pow><tgh>1</tgh><rulelist><rule xmlns:xsi="http://www.w3.org/2001/XMLSchema-instance" xsi:type="rule">{T}: Vithian Stinger deals 1 damage to target creature or player.</rule><rule xmlns:xsi="http://www.w3.org/2001/XMLSchema-instance" xsi:type="rule" reminder="{1}{R}: Return this card from your graveyard to the battlefield. It gains haste. Exile it at the beginning of the next end step or if it would leave the battlefield. Unearth only as a sorcery.">Unearth {1}{R}</rule></rulelist></card><card><name>Volcanic Submersion</name><cost>4R</cost><typelist><type>Sorcery</type></typelist><rulelist><rule xmlns:xsi="http://www.w3.org/2001/XMLSchema-instance" xsi:type="rule">Destroy target artifact or land.</rule><rule xmlns:xsi="http://www.w3.org/2001/XMLSchema-instance" xsi:type="rule" reminder="{2}, Discard this card: Draw a card.">Cycling {2}</rule></rulelist></card><card><name>Waveskimmer Aven</name><cost>2GWU</cost><typelist><type>Creature</type><type>Bird</type><type>Soldier</type></typelist><pow>2</pow><tgh>4</tgh><rulelist><rule xmlns:xsi="http://www.w3.org/2001/XMLSchema-instance" xsi:type="rule">Flying</rule><rule xmlns:xsi="http://www.w3.org/2001/XMLSchema-instance" xsi:type="rule" reminder="Whenever a creature you control attacks alone, that creature gets +1/+1 until end of turn.">Exalted</rule></rulelist></card><card><name>Welkin Guide</name><cost>4W</cost><typelist><type>Creature</type><type>Bird</type><type>Cleric</type></typelist><pow>2</pow><tgh>2</tgh><rulelist><rule xmlns:xsi="http://www.w3.org/2001/XMLSchema-instance" xsi:type="rule">Flying</rule><rule xmlns:xsi="http://www.w3.org/2001/XMLSchema-instance" xsi:type="rule">When Welkin Guide enters the battlefield, target creature gets +2/+2 and gains flying until end of turn.</rule></rulelist></card><card><name>Where Ancients Tread</name><cost>4R</cost><typelist><type>Enchantment</type></typelist><rulelist><rule xmlns:xsi="http://www.w3.org/2001/XMLSchema-instance" xsi:type="rule">Whenever a creature with power 5 or greater enters the battlefield under your control, you may have Where Ancients Tread deal 5 damage to target creature or player.</rule></rulelist></card><card><name>Wild Nacatl</name><cost>G</cost><typelist><type>Creature</type><type>Cat</type><type>Warrior</type></typelist><pow>1</pow><tgh>1</tgh><rulelist><rule xmlns:xsi="http://www.w3.org/2001/XMLSchema-instance" xsi:type="rule">Wild Nacatl gets +1/+1 as long as you control a Mountain.</rule><rule xmlns:xsi="http://www.w3.org/2001/XMLSchema-instance" xsi:type="rule">Wild Nacatl gets +1/+1 as long as you control a Plains.</rule></rulelist></card><card><name>Windwright Mage</name><cost>WUB</cost><typelist><type>Artifact</type><type>Creature</type><type>Human</type><type>Wizard</type></typelist><pow>2</pow><tgh>2</tgh><rulelist><rule xmlns:xsi="http://www.w3.org/2001/XMLSchema-instance" xsi:type="rule" reminder="Damage dealt by this creature also causes you to gain that much life.">Lifelink</rule><rule xmlns:xsi="http://www.w3.org/2001/XMLSchema-instance" xsi:type="rule">Windwright Mage has flying as long as an artifact card is in your graveyard.</rule></rulelist></card><card><name>Woolly Thoctar</name><cost>RGW</cost><typelist><type>Creature</type><type>Beast</type></typelist><pow>5</pow><tgh>4</tgh></card><card><name>Yoked Plowbeast</name><cost>5WW</cost><typelist><type>Creature</type><type>Beast</type></typelist><pow>5</pow><tgh>5</tgh><rulelist><rule xmlns:xsi="http://www.w3.org/2001/XMLSchema-instance" xsi:type="rule" reminder="{2}, Discard this card: Draw a card.">Cycling {2}</rule></rulelist></card></deck>